Workbook
Name \p: #REF!
Name \p: #REF!
Name \p: #REF!
Name \p: #REF!
Name _010SpotSales: #REF!
Name _011OffMktSales: #REF!
Name _012EnergySalesComalco: #REF!
Name _013Direct_Supply: #REF!
Name _015_Energy_Sales_ECNZ_Hedges: #REF!
Name _017_EnergyTransmissionRev_TP: #REF!
Name _019Discounts: #REF!
Name _01GEnergy_Sales_ECNZ_Buy_Hedges: #REF!
Name _01H_EnergySales_Other_Hedges: #REF!
Name _01I_EnergySales_InternalHedge: #REF!
Name _01R_EnergySales_ExistingRetail: #REF!
Name _01T_EnergySales_TransaltaLease: #REF!
Name _020_EnergyFuturesTrading: #REF!
Name _051_Lease_RentalIncome: #REF!
Name _052_DividendsIncome: #REF!
Name _053_GainonForeignCurrency: #REF!
Name _054_GainonSaleofFixedAssets: #REF!
Name _055_MiscellaneousIncome: #REF!
Name _070_Steam_HotWaterRevenues: #REF!
Name _112_NZEMCosts_ServiceProvider: #REF!
Name _113_MACSCosts: #REF!
Name _115_Connection_OtherCharges: #REF!
Name _118EnergyCostComalco: #REF!
Name _119Energy_Cost_Direct_Supply: #REF!
Name _11A_MeterReading_TOU: #REF!
Name _11B_MeterLeasing: #REF!
Name _11C_MeterManagement: #REF!
Name _11D_RocMeterReading: #REF!
Name _11MComalcoTransmissionRevenue: #REF!
Name _11N_TiwaiPointTransCharge: #REF!
Name _11P_LineRevenue: #REF!
Name _11QLineCharges: #REF!
Name _120_MARIACosts: #REF!
Name _121AC_ConnectionCharges: #REF!
Name _122HVDC_Charges: #REF!
Name _123_InvoiceProcessing: #REF!
Name _124_RemittanceProcessing: #REF!
Name _125_DataAdministration: #REF!
Name _126_ROCAdministrativeStaff: #REF!
Name _127_ROCCallCentreStaff: #REF!
Name _190_GridExitPoints: #REF!
Name _191_FieldServicescosts: #REF!
Name _192_PulseCosts: #REF!
Name _1HOLOS_ORIENT_P_L_ACT_DL: #REF!
Name _211_Salary_Pay: #REF!
Name _212_Bonus: #REF!
Name _213_TempEmployeesWages: #REF!
Name _214_CapitalisedSalary: #REF!
Name _221_AccidentInsurance: #REF!
Name _223_FringeBenefitTax: #REF!
Name _224_MembershipFees_Staff: #REF!
Name _225_Severance: #REF!
Name _231_RecruitmentCosts: #REF!
Name _241_Training_Conferencecosts: #REF!
Name _242_Training_TRAVEL_ACCOMMcosts: #REF!
Name _251_HumanResourcePrograms: #REF!

Sheet Summary
A1: Fiscal Time Series Historical Indicators 1972 - 2025
A2: Update for Year End 30 June 2025
A3: Published 9 January 2026
A4: Published by the Treasury at https://www.treasury.govt.nz/publications/information-release/data-fiscal-time-series-historical-fiscal-indicators
A6: Click on a group title to access an explanation of the series contained in that group.

Sheet Series Descriptions
B1: Series Descriptions
A140: Magnitude of difference in 1994 transition from cash to accrual
A142: Series | C142: Cash, GST inclusive | D142: Accrual (old-GAAP), GST exclusive | E142: Difference | F142: Notes
A143: Expenses by Function Classification
B144: Social security and welfare, GSF | C144: 10528 | D144: 11473 | E144: =C144-D144 -> -945
B145: Health | C145: 4103 | D145: 4104 | E145: =C145-D145 -> -1
B146: Education | C146: 4631 | D146: 4173 | E146: =C146-D146 -> 458
B147: Core Government Services | C147: 2104 | D147: 1673 | E147: =C147-D147 -> 431
B148: Law and order | C148: 1260 | D148: 1145 | E148: =C148-D148 -> 115
B149: Defence | C149: 1163 | D149: 1049 | E149: =C149-D149 -> 114
B150: Transport and communications | C150: 805 | D150: 733 | E150: =C150-D150 -> 72
B151: Economic and Industrial Services | C151: 909 | D151: 653 | E151: =C151-D151 -> 256
B152: Heritage, culture and recreation; Primary Services, Housing and community development, Other | C152: 114 | D152: 583 | E152: =C152-D152 -> -469 | F152: Relatively large difference due differences in functional classifications
B153: Finance costs | C153: 3557 | D153: 3788 | E153: =C153-D153 -> -231
A155: Financial Net Expenditure (cash)/Core Crown Expenses (accrual) | C155: 29174 | D155: 28476 | E155: =C155-D155 -> 698 | F155: Adding FX net losses of $898m to sum of expenses by function gives core Crown Expenses.
A157: Cash Receipts (cash)/Core Crown Revenue (accrual) | C157: 29598 | D157: 29020 | E157: =C157-D157 -> 578
A159: Adjusted Financial Balance (cash)/Total Crown Operating Balance (accrual) | C159: 792 | D159: 755 | E159: =C159-D159 -> 37 | F159: A full line-by-line reconciliation of the Adjusted Financial Balance can be found in Table 1 on page 6 of the "Fiscal Time Series Explanatory Note".

Sheet Sources
A1: Sources

Sheet Spending
A1: Spending
A3: $ millions | C3: Spending | G3: Core Crown Expense Classes
C4: Financial Net Expenditure | D4: Core Crown Expenses | E4: Total Crown Expenses | G4: Social security and welfare, GSF | H4: Health | I4: Education | J4: Core Government Services | K4: Law and order | L4: Defence | M4: Transport and communications | N4: Economic and Industrial Services | O4: Heritage, culture and recreation; Primary Services, Housing and community development, Environemntal protection, Other | P4: Finance costs | Q4: Net foreign exchange gains(-)/losses
A5: Cash, March Years | B5: 1972 | C5: 1682.8 | G5: 391.9 | H5: 291.8 | I5: 335 | J5: 113.8 | K5: 32.2 | L5: 118.8 | M5: 144.4 | N5: 43.3 | O5: 131.6 | P5: 168
B6: 1973 | C6: 2006.2 | G6: 527.3 | H6: 343.1 | I6: 376.8 | J6: 133.3 | K6: 39.8 | L6: 128.1 | M6: 183.1 | N6: 68.7 | O6: 143.5 | P6: 186.5
B7: 1974 | C7: 2303.9 | G7: 646.8 | H7: 401.1 | I7: 440.2 | J7: 168 | K7: 46.3 | L7: 138.7 | M7: 168.7 | N7: 75.2 | O7: 194.8 | P7: 201.9
B8: 1975 | C8: 2977.7 | G8: 789.5 | H8: 492.3 | I8: 526.6 | J8: 228.4 | K8: 61 | L8: 163 | M8: 211.2 | N8: 145.3 | O8: 313.5 | P8: 221.8
B9: 1976 | C9: 3562 | G9: 997 | H9: 605.7 | I9: 627 | J9: 272.7 | K9: 77.8 | L9: 188.4 | M9: 274.8 | N9: 228.4 | O9: 494.1 | P9: 272.8
B10: 1977 | C10: 3956.9 | G10: 1158.9 | H10: 689.1 | I10: 699.4 | J10: 315.2 | K10: 79.6 | L10: 210.7 | M10: 230.6 | N10: 293.2 | O10: 283.2 | P10: 371.3
B11: 1978 | C11: 4959.1 | G11: 1569.3 | H11: 808.5 | I11: 807.5 | J11: 337.7 | K11: 107.5 | L11: 248.2 | M11: 247.6 | N11: 375.9 | O11: 368.7 | P11: 471.3
B12: 1979 | C12: 6099.5 | G12: 1853.5 | H12: 980.1 | I12: 929.3 | J12: 420 | K12: 139.3 | L12: 293.2 | M12: 279.1 | N12: 486.1 | O12: 507.5 | P12: 595.8
B13: 1980 | C13: 6971.2 | G13: 2175 | H13: 1136.2 | I13: 1009.3 | J13: 467.7 | K13: 164.7 | L13: 340.8 | M13: 265 | N13: 398.5 | O13: 486.6 | P13: 766.4
B14: 1981 | C14: 8517.3 | G14: 2589.7 | H14: 1356.3 | I14: 1292 | J14: 568.4 | K14: 208.8 | L14: 446.4 | M14: 332.6 | N14: 434.7 | O14: 502.5 | P14: 896.9
B15: 1982 | C15: 10407.7 | G15: 3042.3 | H15: 1601.2 | I15: 1493.2 | J15: 673 | K15: 253.5 | L15: 581.1 | M15: 460.6 | N15: 652.4 | O15: 657.7 | P15: 1211
B16: 1983 | C16: 11956.4 | G16: 3744.2 | H16: 1766 | I16: 1638.8 | J16: 707.1 | K16: 266.3 | L16: 644.1 | M16: 495.6 | N16: 742.1 | O16: 710.9 | P16: 1492.6
B17: 1984 | C17: 13424.6 | G17: 4049.4 | H17: 1804.9 | I17: 1674.3 | J17: 729.2 | K17: 271.3 | L17: 660.2 | M17: 537.1 | N17: 896.2 | O17: 996.1 | P17: 2041.9
... B19: 1986 | C19: 16987.2 | G19: 5449.1 | H19: 2309 | I19: 2010.3 | J19: 1048.2 | K19: 391.1 | L19: 852.1 | M19: 865.6 | N19: 755.2 | O19: 460.8 | P19: 3340
B20: 1987† | C20: 20823 | G20: 6479.3 | H20: 2957.3 | I20: 2595.2 | J20: 1205.6 | K20: 520.6 | L20: 1072.1 | M20: 1039.4 | N20: 1007.5 | O20: 476.4 | P20: 4091.9
B21: 1988† | C21: 24905.7 | G21: 7791.9 | H21: 3387.5 | I21: 3118.2 | J21: 1798.2 | K21: 681.4 | L21: 1257.6 | M21: 654.8 | N21: 1006.6 | O21: 343 | P21: 4970.9
B22: 1989† | C22: 26427.5 | G22: 9123.3 | H22: 3639.3 | I22: 3569.2 | J22: 1886.1 | K22: 863.7 | L22: 1366.9 | M22: 672 | N22: 872.1 | O22: 355.7 | P22: 4492.5
A23: Cash, June Years | B23: 1990† | C23: 29294.4 | G23: 10319.8 | H23: 3782.2 | I23: 4068.2 | J23: 2376.5 | K23: 958.7 | L23: 1352.3 | M23: 888.3 | N23: 870.2 | O23: 289.3 | P23: 4724.5
B24: 1991† | C24: 30298 | G24: 10317 | H24: 3986 | I24: 4401 | J24: 2446.9 | K24: 1003.9 | L24: 1319.2 | M24: 826 | N24: 1038.8 | O24: 335.2 | P24: 4624
B25: 1992† | C25: 29174 | G25: 10620 | H25: 3855 | I25: 4467 | J25: 2084.7 | K25: 1036.3 | L25: 1238 | M25: 816 | N25: 640.7 | O25: 269.3 | P25: 4147
B26: 1993† | C26: 29418 | G26: 10697.2 | H26: 3873.6 | I26: 4503.6 | J26: 2179.1 | K26: 1281.4 | L26: 1171.4 | M26: 717.6 | N26: 944.1 | O26: 149.9 | P26: 3898.5
A27: old-GAAP | B27: 1994* | D27: 28476 | G27: =10725+748 -> 11473 | H27: 4104 | I27: 4173 | J27: 1673 | K27: =1145 -> 1145 | L27: 1049 | M27: 733 | N27: 653 | O27: 583 | P27: 3788 | Q27: -898
B28: 1995* | D28: 29214 | G28: =10851+872 -> 11723 | H28: 4367 | I28: 4338 | J28: 1300 | K28: 1176 | L28: 1013 | M28: 714 | N28: 622 | O28: 755 | P28: 3757 | Q28: -551
B29: 1996* | D29: 30483 | G29: =11230+1009 -> 12239 | H29: 4672 | I29: 4463 | J29: 1508 | K29: 1222 | L29: 970 | M29: 737 | N29: 950 | O29: 622 | P29: 3703 | Q29: -603
A30: IFRS, June Years | B30: 1997 | D30: 31367.962 | E30: 37599.962 | G30: 12180.962 | H30: 5029 | I30: 4817 | J30: 1956 | K30: 1266 | L30: 946 | M30: 797 | N30: 711 | O30: 720 | P30: 2945
B31: 1998 | D31: 32981.947 | E31: 38766.947 | G31: 13024.947 | H31: 5361 | I31: 5162 | J31: 1858 | K31: 1329 | L31: 1065 | M31: 850 | N31: 769 | O31: 890 | P31: 2673
B32: 1999 | D32: 33938.571 | E32: 39837.571 | G32: 13435.571 | H32: 5875 | I32: 5337 | J32: 1984 | K32: 1482 | L32: 1022 | M32: 923 | N32: 813 | O32: 700 | P32: 2367
B33: 2000 | D33: 34828.526 | E33: 41017.946 | G33: 13499.526 | H33: 6146 | I33: 5712 | J33: 1992 | K33: 1509 | L33: 1163 | M33: 929 | N33: 881 | O33: 792 | P33: 2205
B34: 2001^ | D34: 36558.549 | E34: 43518.019 | G34: 13781.549 | H34: 6660 | I34: 6136 | J34: 2148 | K34: 1541 | L34: 1242 | M34: 905 | N34: 1037 | O34: 804 | P34: 2304
B35: 2002^ | D35: 37512.702 | E35: 47202.446 | G35: 14161.406 | H35: 7032 | I35: 6473 | J35: 1890 | K35: 1733 | L35: 1162 | M35: 989 | N35: 1013 | O35: 941.296 | P35: 2118
B36: 2003^ | D36: 39897.483 | E36: 51948.612 | G36: 14448.87 | H36: 7501 | I36: 7016 | J36: 2130 | K36: 1734 | L36: 1199 | M36: 1408 | N36: 1054 | O36: 1046.613 | P36: 2360
B37: 2004^ | D37: 41882.174 | E37: 53210.765 | G37: 14843.556 | H37: 8111 | I37: 7585 | J37: 2091 | K37: 1843 | L37: 1311 | M37: 1461 | N37: 1192 | O37: 1192.618 | P37: 2252
A38: PBE Standards, June Years | B38: 2005^ | D38: 44660 | E38: 57687 | G38: 15253 | H38: 8813 | I38: 7930 | J38: 2567 | K38: 1889 | L38: 1275 | M38: 1635 | N38: 1444 | O38: 1580 | P38: 2274
B39: 2006^ | D39: 49084 | E39: 63703 | G39: 16212 | H39: 9547 | I39: 9914 | J39: 2507 | K39: 2146 | L39: 1383 | M39: 1818 | N39: 1592 | O39: 1609 | P39: 2356
B40: 2007^ | D40: 53764 | E40: 68055 | G40: 17266 | H40: 10355 | I40: 9269 | J40: 4817 | K40: 2606 | L40: 1517 | M40: 2405 | N40: 1595 | O40: 1605 | P40: 2329
B41: 2008^ | D41: 56753 | E41: 75096 | G41: 18420 | H41: 11297 | I41: 9551 | J41: 3371 | K41: 2797 | L41: 1562 | M41: 2244 | N41: 2889 | O41: 2162 | P41: 2460
B42: 2009^ | D42: 63711 | E42: 82592 | G42: 19844 | H42: 12368 | I42: 11455 | J42: 5293 | K42: 2992 | L42: 1757 | M42: 2663 | N42: 2960 | O42: 1950 | P42: 2429
B43: 2010^ | D43: 63554 | E43: 80048 | G43: 21142 | H43: 13128 | I43: 11724 | J43: 2974 | K43: 3103 | L43: 1814 | M43: 2345 | N43: 2806 | O43: 2207 | P43: 2311
B44: 2011^ | D44: 70099 | E44: 99043 | G44: 22029 | H44: 13753 | I44: 11650 | J44: 5563 | K44: 3312 | L44: 1809 | M44: 2281 | N44: 2542 | O44: 4094 | P44: 3066
B45: 2012^ | D45: 68939 | E45: 91989 | G45: 22148 | H45: 14160 | I45: 11654 | J45: 5428 | K45: 3338 | L45: 1736 | M45: 2232 | N45: 2073 | O45: 2659 | P45: 3511
B46: 2013^ | D46: 69962 | E46: 90030 | G46: 22737 | H46: 14498 | I46: 12504 | J46: 4294 | K46: 3394 | L46: 1804 | M46: 2255 | N46: 1978 | O46: 2879 | P46: 3619
B47: 2014^ | D47: 71174 | E47: 91179 | G47: 23308 | H47: 14898 | I47: 12300 | J47: 4502 | K47: 3463 | L47: 1811 | M47: 2237 | N47: 2058 | O47: 2977 | P47: 3620
B48: 2015^ | D48: 72363 | E48: 93064 | G48: 23881 | H48: 15058 | I48: 12879 | J48: 4134 | K48: 3515 | L48: 1961 | M48: 2291 | N48: 2228 | O48: 2633 | P48: 3783
B49: 2016^ | D49: 73929 | E49: 95137 | G49: 24352 | H49: 15626 | I49: 13158 | J49: 4102 | K49: 3648 | L49: 2026 | M49: 2178 | N49: 2107 | O49: 3142 | P49: 3590
B50: 2017^ | D50: 76339 | E50: 99007 | G50: 25511 | H50: 16223 | I50: 13281 | J50: 3957 | K50: 3882 | L50: 2146 | M50: 2176 | N50: 2544 | O50: 3085 | P50: 3534
... B52: 2019^# | D52: 86959 | E52: 111376 | G52: 28806 | H52: 18268 | I52: 14293 | J52: 5166 | K52: 4625 | L52: 2395 | M52: 2889 | N52: 3006 | O52: 3820 | P52: 3691
B53: 2020 | D53: 108832 | E53: 138916 | G53: 44028 | H53: 19891 | I53: 16322 | J53: 6083 | K53: 4911 | L53: 2499 | M53: 3179 | N53: 3988 | O53: =D53-SUM(G53:N53,P53) -> 4703 | P53: 3228
B54: 2021 | D54: 107764 | E54: 133722 | G54: 36759 | H54: 22784 | I54: 16039 | J54: 5754 | K54: 5202 | L54: 2664 | M54: 5656 | N54: 4481 | O54: 6507 | P54: 1918
B55: 2022 | D55: 125641 | E55: 150956 | G55: 42954 | H55: 27781 | I55: 18023 | J55: 5720 | K55: 5444 | L55: 2832 | M55: 4657 | N55: 8078 | O55: 7268 | P55: 2884
B56: 2023 | D56: 127574 | E56: 161822 | G56: =41514+61 -> 41575 | H56: 28489 | I56: 18403 | J56: 6806 | K56: 6165 | L56: 2886 | M56: 5472 | N56: 3690 | O56: 7519 | P56: 6569
B57: 2024 | D57: 138998 | E57: 180061 | G57: 44658 | H57: 29999 | I57: 20223 | J57: 8468 | K57: 6527 | L57: 3163 | M57: 5487 | N57: 4010 | O57: 7520 | P57: 8943
B58: 2025 | D58: 141675 | E58: 183502 | G58: 47568 | H58: 30311 | I58: 20895 | J58: 7908 | K58: 6734 | L58: 3271 | M58: 5472 | N58: 3514 | O58: 7140 | P58: 8862
A60: * GAAP data for these years has not been backdated on IFRS basis
A61: † Data for these years inclusive of GST
A62: See | B62: magnitude of difference in 1994 in transition from cash to accrual
A63: 1 Includes Heritage, culture and recreation, primary services, Housing and Community devlopment; and environmental protection
A64: ^ Total Crown expenses have been restated to exclude Income Related Rent Subsidy expense between government reporting entities
A65: # 2019 results have been restated in the adoption of new PBE standards. Further information can be found in note 28 of the 2019/20 financial statements of government.
A69: % GDP | C69: Spending | G69: Core Crown Expense Classes
C70: Financial Net Expenditure | D70: Core Crown Expenses | E70: Total Crown Expenses | G70: Social security and welfare, GSF | H70: Health | I70: Education | J70: Core government services | K70: Law and order | L70: Defence | M70: Transport and communications | N70: Economic and industrial services | O70: Heritage, culture and recreation; Primary Services, Housing and community development, Other | P70: Finance costs | Q70: Net foreign exchange gains(-)/losses
A71: Cash, March Years | B71: 1972 | C71: =C5/'Nominal GDP'!$C5 -> 0.24074392 | G71: =G5/'Nominal GDP'!$C5 -> 0.056065808 | H71: =H5/'Nominal GDP'!$C5 -> 0.041745351 | I71: =I5/'Nominal GDP'!$C5 -> 0.047925608 | J71: =J5/'Nominal GDP'!$C5 -> 0.016280401 | K71: =K5/'Nominal GDP'!$C5 -> 0.0046065808 | L71: =L5/'Nominal GDP'!$C5 -> 0.016995708 | M71: =M5/'Nominal GDP'!$C5 -> 0.020658083 | N71: =N5/'Nominal GDP'!$C5 -> 0.0061945637 | ... P71: =P5/'Nominal GDP'!$C5 -> 0.024034335
B72: 1973 | C72: =C6/'Nominal GDP'!$C6 -> 0.24829208 | G72: =G6/'Nominal GDP'!$C6 -> 0.065259901 | H72: =H6/'Nominal GDP'!$C6 -> 0.042462871 | I72: =I6/'Nominal GDP'!$C6 -> 0.046633663 | J72: =J6/'Nominal GDP'!$C6 -> 0.016497525 | K72: =K6/'Nominal GDP'!$C6 -> 0.0049257426 | L72: =L6/'Nominal GDP'!$C6 -> 0.01585396 | M72: =M6/'Nominal GDP'!$C6 -> 0.022660891 | N72: =N6/'Nominal GDP'!$C6 -> 0.0085024752 | ... P72: =P6/'Nominal GDP'!$C6 -> 0.023081683
B73: 1974 | C73: =C7/'Nominal GDP'!$C7 -> 0.24611687 | G73: =G7/'Nominal GDP'!$C7 -> 0.069095182 | H73: =H7/'Nominal GDP'!$C7 -> 0.042847986 | I73: =I7/'Nominal GDP'!$C7 -> 0.047024891 | J73: =J7/'Nominal GDP'!$C7 -> 0.017946801 | K73: =K7/'Nominal GDP'!$C7 -> 0.0049460528 | L73: =L7/'Nominal GDP'!$C7 -> 0.014816793 | M73: =M7/'Nominal GDP'!$C7 -> 0.018021579 | N73: =N7/'Nominal GDP'!$C7 -> 0.0080333298 | ... P73: =P7/'Nominal GDP'!$C7 -> 0.021568209
B74: 1975 | C74: =C8/'Nominal GDP'!$C8 -> 0.29184554 | G74: =G8/'Nominal GDP'!$C8 -> 0.077379202 | H74: =H8/'Nominal GDP'!$C8 -> 0.048250515 | I74: =I8/'Nominal GDP'!$C8 -> 0.051612271 | J74: =J8/'Nominal GDP'!$C8 -> 0.022385573 | K74: =K8/'Nominal GDP'!$C8 -> 0.0059786337 | L74: =L8/'Nominal GDP'!$C8 -> 0.015975693 | M74: =M8/'Nominal GDP'!$C8 -> 0.020699794 | N74: =N8/'Nominal GDP'!$C8 -> 0.01424091 | ... P74: =P8/'Nominal GDP'!$C8 -> 0.021738704
B75: 1976 | C75: =C9/'Nominal GDP'!$C9 -> 0.30957761 | G75: =G9/'Nominal GDP'!$C9 -> 0.086650443 | H75: =H9/'Nominal GDP'!$C9 -> 0.0526421 | I75: =I9/'Nominal GDP'!$C9 -> 0.054493308 | J75: =J9/'Nominal GDP'!$C9 -> 0.023700678 | K75: =K9/'Nominal GDP'!$C9 -> 0.0067616896 | L75: =L9/'Nominal GDP'!$C9 -> 0.016374066 | M75: =M9/'Nominal GDP'!$C9 -> 0.023883191 | N75: =N9/'Nominal GDP'!$C9 -> 0.019850513 | ... P75: =P9/'Nominal GDP'!$C9 -> 0.023709369
B76: 1977 | C76: =C10/'Nominal GDP'!$C10 -> 0.28320212 | G76: =G10/'Nominal GDP'!$C10 -> 0.08294446 | H76: =H10/'Nominal GDP'!$C10 -> 0.049320069 | I76: =I10/'Nominal GDP'!$C10 -> 0.050057257 | J76: =J10/'Nominal GDP'!$C10 -> 0.022559405 | K76: =K10/'Nominal GDP'!$C10 -> 0.0056971085 | L76: =L10/'Nominal GDP'!$C10 -> 0.01508016 | M76: =M10/'Nominal GDP'!$C10 -> 0.016504437 | N76: =N10/'Nominal GDP'!$C10 -> 0.020984827 | ... P76: =P10/'Nominal GDP'!$C10 -> 0.026574578
B77: 1978 | C77: =C11/'Nominal GDP'!$C11 -> 0.31653156 | G77: =G11/'Nominal GDP'!$C11 -> 0.10016595 | H77: =H11/'Nominal GDP'!$C11 -> 0.051605285 | I77: =I11/'Nominal GDP'!$C11 -> 0.051541457 | J77: =J11/'Nominal GDP'!$C11 -> 0.021554861 | K77: =K11/'Nominal GDP'!$C11 -> 0.0068615561 | L77: =L11/'Nominal GDP'!$C11 -> 0.015842216 | M77: =M11/'Nominal GDP'!$C11 -> 0.015803919 | N77: =N11/'Nominal GDP'!$C11 -> 0.023993107 | ... P77: =P11/'Nominal GDP'!$C11 -> 0.030082339
B78: 1979 | C78: =C12/'Nominal GDP'!$C12 -> 0.34247614 | G78: =G12/'Nominal GDP'!$C12 -> 0.10407075 | H78: =H12/'Nominal GDP'!$C12 -> 0.055030882 | I78: =I12/'Nominal GDP'!$C12 -> 0.052178551 | J78: =J12/'Nominal GDP'!$C12 -> 0.023582257 | K78: =K12/'Nominal GDP'!$C12 -> 0.0078214486 | L78: =L12/'Nominal GDP'!$C12 -> 0.016462661 | M78: =M12/'Nominal GDP'!$C12 -> 0.015670971 | N78: =N12/'Nominal GDP'!$C12 -> 0.027293655 | ... P78: =P12/'Nominal GDP'!$C12 -> 0.033453116
B79: 1980 | C79: =C13/'Nominal GDP'!$C13 -> 0.33929719 | G79: =G13/'Nominal GDP'!$C13 -> 0.10586002 | H79: =H13/'Nominal GDP'!$C13 -> 0.055300302 | I79: =I13/'Nominal GDP'!$C13 -> 0.049123917 | J79: =J13/'Nominal GDP'!$C13 -> 0.022763555 | K79: =K13/'Nominal GDP'!$C13 -> 0.0080161589 | L79: =L13/'Nominal GDP'!$C13 -> 0.01658717 | M79: =M13/'Nominal GDP'!$C13 -> 0.012897888 | N79: =N13/'Nominal GDP'!$C13 -> 0.019395503 | ... P79: =P13/'Nominal GDP'!$C13 -> 0.037301665
B80: 1981 | C80: =C14/'Nominal GDP'!$C14 -> 0.35506503 | G80: =G14/'Nominal GDP'!$C14 -> 0.10795815 | H80: =H14/'Nominal GDP'!$C14 -> 0.05654077 | I80: =I14/'Nominal GDP'!$C14 -> 0.053860263 | J80: =J14/'Nominal GDP'!$C14 -> 0.023695181 | K80: =K14/'Nominal GDP'!$C14 -> 0.0087043522 | L80: =L14/'Nominal GDP'!$C14 -> 0.018609305 | M80: =M14/'Nominal GDP'!$C14 -> 0.013865266 | N80: =N14/'Nominal GDP'!$C14 -> 0.018121561 | ... P80: =P14/'Nominal GDP'!$C14 -> 0.037389528
B81: 1982 | C81: =C15/'Nominal GDP'!$C15 -> 0.35854003 | G81: =G15/'Nominal GDP'!$C15 -> 0.1048057 | H81: =H15/'Nominal GDP'!$C15 -> 0.055160535 | I81: =I15/'Nominal GDP'!$C15 -> 0.051439989 | J81: =J15/'Nominal GDP'!$C15 -> 0.023184512 | K81: =K15/'Nominal GDP'!$C15 -> 0.0087329475 | L81: =L15/'Nominal GDP'!$C15 -> 0.020018603 | M81: =M15/'Nominal GDP'!$C15 -> 0.015867438 | N81: =N15/'Nominal GDP'!$C15 -> 0.022474852 | ... P81: =P15/'Nominal GDP'!$C15 -> 0.041718341
B82: 1983 | C82: =C16/'Nominal GDP'!$C16 -> 0.3576976 | G82: =G16/'Nominal GDP'!$C16 -> 0.1120146 | H82: =H16/'Nominal GDP'!$C16 -> 0.052833124 | I82: =I16/'Nominal GDP'!$C16 -> 0.049027703 | J82: =J16/'Nominal GDP'!$C16 -> 0.021154191 | K82: =K16/'Nominal GDP'!$C16 -> 0.0079668522 | L82: =L16/'Nominal GDP'!$C16 -> 0.019269431 | M82: =M16/'Nominal GDP'!$C16 -> 0.014826782 | N82: =N16/'Nominal GDP'!$C16 -> 0.02220128 | ... P82: =P16/'Nominal GDP'!$C16 -> 0.044653862
B83: 1984 | C83: =C17/'Nominal GDP'!$C17 -> 0.36036292 | G83: =G17/'Nominal GDP'!$C17 -> 0.10869997 | H83: =H17/'Nominal GDP'!$C17 -> 0.048449789 | I83: =I17/'Nominal GDP'!$C17 -> 0.044944031 | J83: =J17/'Nominal GDP'!$C17 -> 0.019574262 | K83: =K17/'Nominal GDP'!$C17 -> 0.007282635 | L83: =L17/'Nominal GDP'!$C17 -> 0.017722063 | M83: =M17/'Nominal GDP'!$C17 -> 0.014417631 | N83: =N17/'Nominal GDP'!$C17 -> 0.024057123 | ... P83: =P17/'Nominal GDP'!$C17 -> 0.054811693
... B85: 1986 | C85: =C19/'Nominal GDP'!$C19 -> 0.34824822 | G85: =G19/'Nominal GDP'!$C19 -> 0.11170996 | H85: =H19/'Nominal GDP'!$C19 -> 0.047335944 | I85: =I19/'Nominal GDP'!$C19 -> 0.041212407 | J85: =J19/'Nominal GDP'!$C19 -> 0.021488755 | K85: =K19/'Nominal GDP'!$C19 -> 0.0080177945 | L85: =L19/'Nominal GDP'!$C19 -> 0.017468583 | M85: =M19/'Nominal GDP'!$C19 -> 0.017745341 | N85: =N19/'Nominal GDP'!$C19 -> 0.015482072 | ... P85: =P19/'Nominal GDP'!$C19 -> 0.068472088
B86: 1987† | C86: =C20/'Nominal GDP'!$C20 -> 0.35930841 | G86: =G20/'Nominal GDP'!$C20 -> 0.11180267 | H86: =H20/'Nominal GDP'!$C20 -> 0.051029282 | I86: =I20/'Nominal GDP'!$C20 -> 0.044781116 | J86: =J20/'Nominal GDP'!$C20 -> 0.020803065 | K86: =K20/'Nominal GDP'!$C20 -> 0.0089831415 | L86: =L20/'Nominal GDP'!$C20 -> 0.018499474 | M86: =M20/'Nominal GDP'!$C20 -> 0.017935223 | N86: =N20/'Nominal GDP'!$C20 -> 0.017384777 | ... P86: =P20/'Nominal GDP'!$C20 -> 0.070607216
B87: 1988† | C87: =C21/'Nominal GDP'!$C21 -> 0.3821827 | G87: =G21/'Nominal GDP'!$C21 -> 0.11956819 | H87: =H21/'Nominal GDP'!$C21 -> 0.051981831 | I87: =I21/'Nominal GDP'!$C21 -> 0.047849372 | J87: =J21/'Nominal GDP'!$C21 -> 0.027593721 | K87: =K21/'Nominal GDP'!$C21 -> 0.010456213 | L87: =L21/'Nominal GDP'!$C21 -> 0.019298111 | M87: =M21/'Nominal GDP'!$C21 -> 0.01004803 | N87: =N21/'Nominal GDP'!$C21 -> 0.015446468 | ... P87: =P21/'Nominal GDP'!$C21 -> 0.076279405
B88: 1989† | C88: =C22/'Nominal GDP'!$C22 -> 0.3741735 | G88: =G22/'Nominal GDP'!$C22 -> 0.12917215 | H88: =H22/'Nominal GDP'!$C22 -> 0.051526993 | I88: =I22/'Nominal GDP'!$C22 -> 0.050534483 | J88: =J22/'Nominal GDP'!$C22 -> 0.026704328 | K88: =K22/'Nominal GDP'!$C22 -> 0.012228688 | L88: =L22/'Nominal GDP'!$C22 -> 0.01935324 | M88: =M22/'Nominal GDP'!$C22 -> 0.0095145054 | N88: =N22/'Nominal GDP'!$C22 -> 0.012347619 | ... P88: =P22/'Nominal GDP'!$C22 -> 0.063607017
A89: Cash, June Years | B89: 1990† | C89: =C23/'Nominal GDP'!$C23 -> 0.38986425 | G89: =G23/'Nominal GDP'!$C23 -> 0.13734096 | H89: =H23/'Nominal GDP'!$C23 -> 0.050335374 | I89: =I23/'Nominal GDP'!$C23 -> 0.054141602 | J89: =J23/'Nominal GDP'!$C23 -> 0.031627628 | K89: =K23/'Nominal GDP'!$C23 -> 0.01275885 | L89: =L23/'Nominal GDP'!$C23 -> 0.017997072 | M89: =M23/'Nominal GDP'!$C23 -> 0.011821932 | N89: =N23/'Nominal GDP'!$C23 -> 0.011581049 | ... P89: =P23/'Nominal GDP'!$C23 -> 0.062875965
B90: 1991† | C90: =C24/'Nominal GDP'!$C24 -> 0.39887308 | G90: =G24/'Nominal GDP'!$C24 -> 0.13582327 | H90: =H24/'Nominal GDP'!$C24 -> 0.052475678 | I90: =I24/'Nominal GDP'!$C24 -> 0.057939151 | J90: =J24/'Nominal GDP'!$C24 -> 0.032213431 | K90: =K24/'Nominal GDP'!$C24 -> 0.01321634 | L90: =L24/'Nominal GDP'!$C24 -> 0.017367264 | M90: =M24/'Nominal GDP'!$C24 -> 0.010874287 | N90: =N24/'Nominal GDP'!$C24 -> 0.013675799 | ... P90: =P24/'Nominal GDP'!$C24 -> 0.060874946
B91: 1992† | C91: =C25/'Nominal GDP'!$C25 -> 0.37925745 | G91: =G25/'Nominal GDP'!$C25 -> 0.13805834 | H91: =H25/'Nominal GDP'!$C25 -> 0.050114399 | I91: =I25/'Nominal GDP'!$C25 -> 0.058070303 | J91: =J25/'Nominal GDP'!$C25 -> 0.027100775 | K91: =K25/'Nominal GDP'!$C25 -> 0.013471738 | L91: =L25/'Nominal GDP'!$C25 -> 0.016093807 | M91: =M25/'Nominal GDP'!$C25 -> 0.010607873 | N91: =N25/'Nominal GDP'!$C25 -> 0.0083290001 | ... P91: =P25/'Nominal GDP'!$C25 -> 0.053910353
B92: 1993† | C92: =C26/'Nominal GDP'!$C26 -> 0.37074191 | G92: =G26/'Nominal GDP'!$C26 -> 0.13481203 | H92: =H26/'Nominal GDP'!$C26 -> 0.04881725 | I92: =I26/'Nominal GDP'!$C26 -> 0.056756859 | J92: =J26/'Nominal GDP'!$C26 -> 0.027462224 | K92: =K26/'Nominal GDP'!$C26 -> 0.016148912 | L92: =L26/'Nominal GDP'!$C26 -> 0.014762631 | M92: =M26/'Nominal GDP'!$C26 -> 0.0090435922 | N92: =N26/'Nominal GDP'!$C26 -> 0.011898071 | ... P92: =P26/'Nominal GDP'!$C26 -> 0.049131054
A93: old-GAAP | B93: 1994* | D93: =D27/'Nominal GDP'!$C27 -> 0.33099697 | G93: =G27/'Nominal GDP'!$C27 -> 0.13335891 | H93: =H27/'Nominal GDP'!$C27 -> 0.047703735 | I93: =I27/'Nominal GDP'!$C27 -> 0.048505771 | J93: =J27/'Nominal GDP'!$C27 -> 0.019446479 | K93: =K27/'Nominal GDP'!$C27 -> 0.013309156 | L93: =L27/'Nominal GDP'!$C27 -> 0.012193279 | M93: =M27/'Nominal GDP'!$C27 -> 0.0085201846 | N93: =N27/'Nominal GDP'!$C27 -> 0.0075902872 | ... Q93: =Q27/'Nominal GDP'!$C27 -> -0.010438098
B94: 1995* | D94: =D28/'Nominal GDP'!$C28 -> 0.31789939 | G94: =G28/'Nominal GDP'!$C28 -> 0.12756673 | H94: =H28/'Nominal GDP'!$C28 -> 0.047520594 | I94: =I28/'Nominal GDP'!$C28 -> 0.047205023 | J94: =J28/'Nominal GDP'!$C28 -> 0.014146272 | K94: =K28/'Nominal GDP'!$C28 -> 0.012796936 | L94: =L28/'Nominal GDP'!$C28 -> 0.011023211 | M94: =M28/'Nominal GDP'!$C28 -> 0.0077695681 | N94: =N28/'Nominal GDP'!$C28 -> 0.0067684473 | ... Q94: =Q28/'Nominal GDP'!$C28 -> -0.0059958432
B95: 1996* | D95: =D29/'Nominal GDP'!$C29 -> 0.31242826 | G95: =G29/'Nominal GDP'!$C29 -> 0.12544072 | H95: =H29/'Nominal GDP'!$C29 -> 0.047884552 | I95: =I29/'Nominal GDP'!$C29 -> 0.045742457 | J95: =J29/'Nominal GDP'!$C29 -> 0.015455887 | K95: =K29/'Nominal GDP'!$C29 -> 0.012524598 | L95: =L29/'Nominal GDP'!$C29 -> 0.0099417842 | M95: =M29/'Nominal GDP'!$C29 -> 0.0075537061 | N95: =N29/'Nominal GDP'!$C29 -> 0.009736799 | ... Q95: =Q29/'Nominal GDP'!$C29 -> -0.006180305
A96: IFRS, June Years | B96: 1997 | D96: =D30/'Nominal GDP'!$C30 -> 0.30721279 | E96: =E30/'Nominal GDP'!$C30 -> 0.368248 | G96: =G30/'Nominal GDP'!$C30 -> 0.11929839 | H96: =H30/'Nominal GDP'!$C30 -> 0.04925322 | I96: =I30/'Nominal GDP'!$C30 -> 0.047176926 | J96: =J30/'Nominal GDP'!$C30 -> 0.01915675 | K96: =K30/'Nominal GDP'!$C30 -> 0.012399001 | L96: =L30/'Nominal GDP'!$C30 -> 0.0092649723 | M96: =M30/'Nominal GDP'!$C30 -> 0.0078056902 | N96: =N30/'Nominal GDP'!$C30 -> 0.00696342 | ... P96: =P30/'Nominal GDP'!$C30 -> 0.028842858
B97: 1998 | D97: =D31/'Nominal GDP'!$C31 -> 0.31435928 | E97: =E31/'Nominal GDP'!$C31 -> 0.36949758 | G97: =G31/'Nominal GDP'!$C31 -> 0.12414407 | H97: =H31/'Nominal GDP'!$C31 -> 0.051097047 | I97: =I31/'Nominal GDP'!$C31 -> 0.049200328 | J97: =J31/'Nominal GDP'!$C31 -> 0.017709068 | K97: =K31/'Nominal GDP'!$C31 -> 0.012667035 | L97: =L31/'Nominal GDP'!$C31 -> 0.010150784 | M97: =M31/'Nominal GDP'!$C31 -> 0.008101565 | N97: =N31/'Nominal GDP'!$C31 -> 0.0073295335 | ... P97: =P31/'Nominal GDP'!$C31 -> 0.025477039
B98: 1999 | D98: =D32/'Nominal GDP'!$C32 -> 0.31367677 | E98: =E32/'Nominal GDP'!$C32 -> 0.36819819 | G98: =G32/'Nominal GDP'!$C32 -> 0.12417808 | H98: =H32/'Nominal GDP'!$C32 -> 0.054299604 | I98: =I32/'Nominal GDP'!$C32 -> 0.049327147 | J98: =J32/'Nominal GDP'!$C32 -> 0.018337092 | K98: =K32/'Nominal GDP'!$C32 -> 0.013697364 | L98: =L32/'Nominal GDP'!$C32 -> 0.0094458205 | M98: =M32/'Nominal GDP'!$C32 -> 0.0085308144 | N98: =N32/'Nominal GDP'!$C32 -> 0.007514141 | ... P98: =P32/'Nominal GDP'!$C32 -> 0.021876964
B99: 2000 | D99: =D33/'Nominal GDP'!$C33 -> 0.30374421 | E99: =E33/'Nominal GDP'!$C33 -> 0.35772297 | G99: =G33/'Nominal GDP'!$C33 -> 0.11773117 | H99: =H33/'Nominal GDP'!$C33 -> 0.053600084 | I99: =I33/'Nominal GDP'!$C33 -> 0.049815112 | J99: =J33/'Nominal GDP'!$C33 -> 0.017372497 | K99: =K33/'Nominal GDP'!$C33 -> 0.01316019 | L99: =L33/'Nominal GDP'!$C33 -> 0.010142678 | M99: =M33/'Nominal GDP'!$C33 -> 0.0081019326 | N99: =N33/'Nominal GDP'!$C33 -> 0.0076833182 | ... P99: =P33/'Nominal GDP'!$C33 -> 0.019230098
B100: 2001^ | D100: =D34/'Nominal GDP'!$C34 -> 0.29914776 | E100: =E34/'Nominal GDP'!$C34 -> 0.35609504 | G100: =G34/'Nominal GDP'!$C34 -> 0.11277033 | H100: =H34/'Nominal GDP'!$C34 -> 0.054496805 | I100: =I34/'Nominal GDP'!$C34 -> 0.050209068 | J100: =J34/'Nominal GDP'!$C34 -> 0.017576447 | K100: =K34/'Nominal GDP'!$C34 -> 0.012609546 | L100: =L34/'Nominal GDP'!$C34 -> 0.010162918 | M100: =M34/'Nominal GDP'!$C34 -> 0.0074053466 | N100: =N34/'Nominal GDP'!$C34 -> 0.0084854634 | ... P100: =P34/'Nominal GDP'!$C34 -> 0.018852949
B101: 2002^ | D101: =D35/'Nominal GDP'!$C35 -> 0.28868582 | E101: =E35/'Nominal GDP'!$C35 -> 0.36325501 | G101: =G35/'Nominal GDP'!$C35 -> 0.10898167 | H101: =H35/'Nominal GDP'!$C35 -> 0.054116035 | I101: =I35/'Nominal GDP'!$C35 -> 0.049814149 | J101: =J35/'Nominal GDP'!$C35 -> 0.014544839 | K101: =K35/'Nominal GDP'!$C35 -> 0.013336617 | L101: =L35/'Nominal GDP'!$C35 -> 0.0089423824 | M101: =M35/'Nominal GDP'!$C35 -> 0.0076110295 | N101: =N35/'Nominal GDP'!$C35 -> 0.0077957258 | ... P101: =P35/'Nominal GDP'!$C35 -> 0.016299454
B102: 2003^ | D102: =D36/'Nominal GDP'!$C36 -> 0.29084886 | E102: =E36/'Nominal GDP'!$C36 -> 0.37870044 | G102: =G36/'Nominal GDP'!$C36 -> 0.10533089 | H102: =H36/'Nominal GDP'!$C36 -> 0.054681577 | I102: =I36/'Nominal GDP'!$C36 -> 0.051145973 | J102: =J36/'Nominal GDP'!$C36 -> 0.015527498 | K102: =K36/'Nominal GDP'!$C36 -> 0.012640695 | L102: =L36/'Nominal GDP'!$C36 -> 0.008740596 | M102: =M36/'Nominal GDP'!$C36 -> 0.010264186 | N102: =N36/'Nominal GDP'!$C36 -> 0.0076835598 | ... P102: =P36/'Nominal GDP'!$C36 -> 0.017204176
B103: 2004^ | D103: =D37/'Nominal GDP'!$C37 -> 0.28382187 | E103: =E37/'Nominal GDP'!$C37 -> 0.36059204 | G103: =G37/'Nominal GDP'!$C37 -> 0.10058995 | H103: =H37/'Nominal GDP'!$C37 -> 0.054965608 | I103: =I37/'Nominal GDP'!$C37 -> 0.051401077 | J103: =J37/'Nominal GDP'!$C37 -> 0.014170027 | K103: =K37/'Nominal GDP'!$C37 -> 0.012489411 | L103: =L37/'Nominal GDP'!$C37 -> 0.0088842205 | M103: =M37/'Nominal GDP'!$C37 -> 0.0099007217 | N103: =N37/'Nominal GDP'!$C37 -> 0.0080777962 | ... P103: =P37/'Nominal GDP'!$C37 -> 0.015261071
A104: PBE Standards, June Years | B104: 2005^ | D104: =D38/'Nominal GDP'!$C38 -> 0.28481598 | E104: =E38/'Nominal GDP'!$C38 -> 0.36789475 | G104: =G38/'Nominal GDP'!$C38 -> 0.097274925 | H104: =H38/'Nominal GDP'!$C38 -> 0.056204282 | I104: =I38/'Nominal GDP'!$C38 -> 0.050573012 | J104: =J38/'Nominal GDP'!$C38 -> 0.01637086 | K104: =K38/'Nominal GDP'!$C38 -> 0.012046963 | L104: =L38/'Nominal GDP'!$C38 -> 0.008131222 | M104: =M38/'Nominal GDP'!$C38 -> 0.010427096 | N104: =N38/'Nominal GDP'!$C38 -> 0.0092090075 | ... P104: =P38/'Nominal GDP'!$C38 -> 0.014502274
B105: 2006^ | D105: =D39/'Nominal GDP'!$C39 -> 0.29845011 | E105: =E39/'Nominal GDP'!$C39 -> 0.3873394 | G105: =G39/'Nominal GDP'!$C39 -> 0.098575363 | H105: =H39/'Nominal GDP'!$C39 -> 0.058049531 | I105: =I39/'Nominal GDP'!$C39 -> 0.060281036 | J105: =J39/'Nominal GDP'!$C39 -> 0.01524355 | K105: =K39/'Nominal GDP'!$C39 -> 0.013048528 | L105: =L39/'Nominal GDP'!$C39 -> 0.0084091863 | M105: =M39/'Nominal GDP'!$C39 -> 0.011054158 | N105: =N39/'Nominal GDP'!$C39 -> 0.0096799888 | ... P105: =P39/'Nominal GDP'!$C39 -> 0.014325411
B106: 2007^ | D106: =D40/'Nominal GDP'!$C40 -> 0.30649253 | E106: =E40/'Nominal GDP'!$C40 -> 0.38796126 | G106: =G40/'Nominal GDP'!$C40 -> 0.098428317 | H106: =H40/'Nominal GDP'!$C40 -> 0.059030767 | I106: =I40/'Nominal GDP'!$C40 -> 0.052839805 | J106: =J40/'Nominal GDP'!$C40 -> 0.02746028 | K106: =K40/'Nominal GDP'!$C40 -> 0.014856029 | L106: =L40/'Nominal GDP'!$C40 -> 0.0086479646 | M106: =M40/'Nominal GDP'!$C40 -> 0.013710188 | N106: =N40/'Nominal GDP'!$C40 -> 0.0090926193 | ... P106: =P40/'Nominal GDP'!$C40 -> 0.013276934
B107: 2008^ | D107: =D41/'Nominal GDP'!$C41 -> 0.30039486 | E107: =E41/'Nominal GDP'!$C41 -> 0.39748476 | G107: =G41/'Nominal GDP'!$C41 -> 0.097497459 | H107: =H41/'Nominal GDP'!$C41 -> 0.059795266 | I107: =I41/'Nominal GDP'!$C41 -> 0.05055365 | J107: =J41/'Nominal GDP'!$C41 -> 0.017842776 | K107: =K41/'Nominal GDP'!$C41 -> 0.014804582 | L107: =L41/'Nominal GDP'!$C41 -> 0.0082676999 | M107: =M41/'Nominal GDP'!$C41 -> 0.011877541 | N107: =N41/'Nominal GDP'!$C41 -> 0.01529154 | ... P107: =P41/'Nominal GDP'!$C41 -> 0.013020833
B108: 2009^ | D108: =D42/'Nominal GDP'!$C42 -> 0.33553827 | E108: =E42/'Nominal GDP'!$C42 -> 0.43497633 | G108: =G42/'Nominal GDP'!$C42 -> 0.10450976 | H108: =H42/'Nominal GDP'!$C42 -> 0.065136904 | I108: =I42/'Nominal GDP'!$C42 -> 0.060328528 | J108: =J42/'Nominal GDP'!$C42 -> 0.027875941 | K108: =K42/'Nominal GDP'!$C42 -> 0.015757569 | L108: =L42/'Nominal GDP'!$C42 -> 0.0092533588 | M108: =M42/'Nominal GDP'!$C42 -> 0.014024869 | N108: =N42/'Nominal GDP'!$C42 -> 0.015589039 | ... P108: =P42/'Nominal GDP'!$C42 -> 0.012792492
...

Sheet Revenue, Surplus measures
A1: Surplus/Deficit, Revenue
A3: $ millions | C3: Surplus/Deficit Measures | I3: Tax and Revenue
C4: Adjusted Financial Balance | D4: Total Crown Operating Balance | E4: Total Crown OBEGALx | F4: Total Crown OBEGAL | G4: Core Crown Residual Cash | I4: Total Crown Tax Receipts | J4: Core Crown Tax Revenue | L4: Cash Receipts | M4: Core Crown Revenue | N4: Total Crown Revenue
A5: Cash, March Years | B5: 1972 | C5: 107.2 | I5: 1707 | L5: 1790
B6: 1973 | C6: 7.2 | I6: 1926.7 | L6: 2013.4
B7: 1974 | C7: 87.7 | I7: 2395 | L7: 2391.6
B8: 1975 | C8: 42.9 | I8: 2865.5 | L8: 3020.6
B9: 1976 | C9: -177.6 | I9: 3185.5 | L9: 3384.4
B10: 1977 | C10: 115.6 | I10: 3845.3 | L10: 4072.5
B11: 1978 | C11: 15.2 | I11: 4626.3 | L11: 4974.3
B12: 1979 | C12: -697.1 | I12: 4989.5 | L12: 5402.4
B13: 1980 | C13: -411.5 | I13: 6019.9 | L13: 6559.7
B14: 1981 | C14: -908.9 | I14: 7050.6 | L14: 7608.4
B15: 1982 | C15: -1029.3 | I15: 8798.2 | L15: 9378.4
B16: 1983 | C16: -1442 | I16: 10097.4 | L16: 10514.4
B17: 1984 | C17: -2275.1 | I17: 10431.4 | L17: 11149.5
... B19: 1986 | C19: -1185.9 | I19: 14235.9 | L19: 15801.3
B20: 1987† | C20: -1830.5 | I20: 17408.1 | L20: 18992.5
B21: 1988† | C21: -1322 | I21: 21528.1 | L21: 23583.7
B22: 1989† | C22: -954.1 | I22: 22864 | L22: 25473.4
A23: Cash, June Years | B23: 1990† | C23: -943.2 | I23: 26198.2 | L23: 28351.2
B24: 1991† | C24: -2558 | I24: 25797 | L24: 29010
B25: 1992† | C25: -2528 | I25: 24843 | L25: 27635
B26: 1993† | C26: -1823 | I26: 25980 | L26: 27629
A27: old-GAAP | B27: 1994* | D27: 755 | F27: -517 | G27: 679 | I27: 27571 | J27: 26542 | M27: 29020
B28: 1995* | D28: 2695 | F28: 2738 | G28: 396 | I28: 29961 | J28: 29026 | M28: 32461
B29: 1996* | D29: 3314 | F29: 2928 | G29: 4932 | I29: 32319 | J29: 30973 | M29: 33799
A30: IFRS, June Years | B30: 1997 | D30: 1863 | F30: 1801 | G30: 3913 | I30: 31731 | J30: 30737 | M30: 33130.962 | N30: 39400.962
B31: 1998 | D31: 2048 | F31: 2345 | G31: 484 | I31: 33059 | J31: 31779 | M31: 34241.947 | N31: 41111.947
B32: 1999 | D32: 1705 | F32: 128 | G32: 2048 | I32: 32384 | J32: 30875 | M32: 32879.571 | N32: 39965.571
B33: 2000 | D33: 1404.58 | F33: 593.58 | G33: -386 | I33: 33864 | J33: 32598 | M33: 34945.526 | N33: 41611.526
B34: 2001^ | D34: 1207.53 | F34: 1421.53 | G34: 349 | I34: 36250 | J34: 35345 | M34: 37841.549 | N34: 44939.549
B35: 2002^ | D35: 2286.4422 | F35: 2471.2152 | G35: 216 | I35: 38862 | J35: 36809 | M35: 39944.685 | N35: 49673.661
B36: 2003^ | D36: 1621.039 | F36: 4365.903 | G36: 1217 | I36: 39842 | J36: 40518 | M36: 43440.393 | N36: 56314.515
B37: 2004^ | D37: 7308.8377 | F37: 5573.1177 | G37: 520 | I37: 42777 | J37: 43358 | M37: 46219.472 | N37: 58783.883
A38: PBE Standards, June Years | B38: 2005^ | D38: 5930.9119 | F38: 7074.7859 | G38: 3104 | I38: 46867 | J38: 47468 | M38: 50809 | N38: 64761
B39: 2006^ | D39: 9541.6391 | F39: 7091.0254 | G39: 2985 | I39: 49706 | J39: 50973 | M39: 55499 | N39: 70794
B40: 2007^ | D40: 8022 | F40: 5860 | G40: 2793 | I40: 52157 | J40: 53477 | M40: 57971 | N40: 73915
B41: 2008^ | D41: 2384 | E41: 5793 | F41: 5637 | G41: 2057 | I41: 55168 | J41: 56747 | M41: 61575 | N41: 80733
B42: 2009^ | D42: -10505 | E42: -3800 | F42: -3893 | G42: -8639 | I42: 51119 | J42: 54681 | M42: 59191 | N42: 78699
B43: 2010^ | D43: -4509 | E43: -7666 | F43: -6315 | G43: -9000 | I43: 50104 | J43: 50744 | M43: 55757 | N43: 73733
B44: 2011^ | D44: -13360 | E44: -19993 | F44: -18396 | G44: -13343 | I44: 50418 | J44: 51557 | M44: 57199 | N44: 80647
B45: 2012^ | D45: -14897 | E45: -11884 | F45: -9240 | G45: -10644 | I45: 53582 | J45: 55081 | M45: 60428 | N45: 82749
B46: 2013^ | D46: 6925 | E46: -5856 | F46: -4414 | G46: -5742 | I46: 56413 | J46: 58651 | M46: 63805 | N46: 85678
B47: 2014^ | D47: 2939 | E47: -3833 | F47: -2802 | G47: -4109 | I47: 59853 | J47: 61563 | M47: 67093 | N47: 88536
B48: 2015^ | D48: 5771 | E48: 333 | F48: 414 | G48: -1827 | I48: 64945 | J48: 66636 | M48: 72213 | N48: 93805
B49: 2016^ | D49: -5369 | E49: 2121 | F49: 1831 | G49: -1322 | I49: 69027 | J49: 70445 | M49: 76121 | N49: 97416
B50: 2017^ | D50: 12317 | E50: 4653 | F50: 4069 | G50: 2574 | I50: 73099 | J50: 75644 | M50: 81782 | N50: 103422
B51: 2018^ | D51: 8396 | E51: 5942 | F51: 5534 | G51: 1346 | I51: 78566 | J51: 80224 | M51: 86778 | N51: 109973
B52: 2019^# | D52: 389 | E52: 8504 | F52: 7429 | G52: -710 | I52: 83017 | J52: 86468 | M52: 93474 | N52: 119142
B53: 2020 | D53: -30040 | E53: -20902 | F53: -23057 | G53: -23692 | I53: 83156 | J53: 85102 | M53: 91923 | N53: 116003
B54: 2021 | D54: 16159 | E54: -2559 | F54: -4560 | G54: -13767 | I54: 95382 | J54: 97983 | M54: 104968 | N54: 129335
B55: 2022 | D55: -16932 | E55: -8664 | F55: -9691 | G55: -27043 | I55: 102712 | J55: 108458 | M55: 117515 | N55: 141627
B56: 2023 | D56: 5321 | E56: -7199 | F56: -9446 | G56: -25648 | I56: 110786 | J56: 112358 | M56: 123398 | N56: 153011
B57: 2024 | D57: -8365 | E57: -8773 | F57: -12854 | G57: -19302 | I57: 116042 | J57: 120566 | M57: 133220 | N57: 167347
B58: 2025 | D58: -4400 | E58: -9306 | F58: -13973 | G58: -5996 | I58: 121183 | J58: 121698 | M58: 134411 | N58: 169811
A60: * GAAP data for Total Crown Operating Balance, core Crown tax Revenue and core Crown Revenue for these years has not been backdated on IFRS basis
A61: † Data for receipts and revenue for these years include GST paid on government purchases
A62: See | B62: magnitude of difference in 1994 in transition from cash to accrual
A63: ^ Total Crown revenue has been restated to exclude Income Related Rent Subsidy between government reporting entities
A64: # 2019 results have been restated in the adoption of new PBE standards. Further information can be found in note 28 of the 2019/20 financial statements of government.
A68: % GDP | C68: Surplus/Deficit Measures | I68: Tax and Revenue
C69: Adjusted Financial Balance | D69: Total Crown Operating Balance | F69: Total Crown OBEGAL | G69: Core Crown Residual Cash | I69: Tax Receipts | J69: Core Crown Tax Revenue | L69: Cash Receipts | M69: Core Crown Revenue | N69: Total Crown Revenue
A70: Cash, March Years | B70: 1972 | C70: ='Revenue, Surplus measures'!C5/'Nominal GDP'!$C5 -> 0.015336195 | I70: ='Revenue, Surplus measures'!I5/'Nominal GDP'!$C5 -> 0.24420601 | L70: ='Revenue, Surplus measures'!L5/'Nominal GDP'!$C5 -> 0.25608011
B71: 1973 | C71: ='Revenue, Surplus measures'!C6/'Nominal GDP'!$C6 -> 0.00089108911 | I71: ='Revenue, Surplus measures'!I6/'Nominal GDP'!$C6 -> 0.23845297 | L71: ='Revenue, Surplus measures'!L6/'Nominal GDP'!$C6 -> 0.24918317
B72: 1974 | C72: ='Revenue, Surplus measures'!C7/'Nominal GDP'!$C7 -> 0.0093686572 | I72: ='Revenue, Surplus measures'!I7/'Nominal GDP'!$C7 -> 0.25584873 | L72: ='Revenue, Surplus measures'!L7/'Nominal GDP'!$C7 -> 0.25548553
B73: 1975 | C73: ='Revenue, Surplus measures'!C8/'Nominal GDP'!$C8 -> 0.0042046457 | I73: ='Revenue, Surplus measures'!I8/'Nominal GDP'!$C8 -> 0.28084877 | L73: ='Revenue, Surplus measures'!L8/'Nominal GDP'!$C8 -> 0.29605018
B74: 1976 | C74: ='Revenue, Surplus measures'!C9/'Nominal GDP'!$C9 -> -0.015435425 | I74: ='Revenue, Surplus measures'!I9/'Nominal GDP'!$C9 -> 0.27685555 | L74: ='Revenue, Surplus measures'!L9/'Nominal GDP'!$C9 -> 0.29414219
B75: 1977 | C75: ='Revenue, Surplus measures'!C10/'Nominal GDP'!$C10 -> 0.0082736902 | I75: ='Revenue, Surplus measures'!I10/'Nominal GDP'!$C10 -> 0.27521472 | L75: ='Revenue, Surplus measures'!L10/'Nominal GDP'!$C10 -> 0.29147581
B76: 1978 | C76: ='Revenue, Surplus measures'!C11/'Nominal GDP'!$C11 -> 0.00097019212 | I76: ='Revenue, Surplus measures'!I11/'Nominal GDP'!$C11 -> 0.29528946 | L76: ='Revenue, Surplus measures'!L11/'Nominal GDP'!$C11 -> 0.31750176
B77: 1979 | C77: ='Revenue, Surplus measures'!C12/'Nominal GDP'!$C12 -> -0.039140932 | I77: ='Revenue, Surplus measures'!I12/'Nominal GDP'!$C12 -> 0.2801516 | L77: ='Revenue, Surplus measures'!L12/'Nominal GDP'!$C12 -> 0.3033352
B78: 1980 | C78: ='Revenue, Surplus measures'!C13/'Nominal GDP'!$C13 -> -0.020028229 | I78: ='Revenue, Surplus measures'!I13/'Nominal GDP'!$C13 -> 0.2929962 | L78: ='Revenue, Surplus measures'!L13/'Nominal GDP'!$C13 -> 0.31926896
B79: 1981 | C79: ='Revenue, Surplus measures'!C14/'Nominal GDP'!$C14 -> -0.037889778 | I79: ='Revenue, Surplus measures'!I14/'Nominal GDP'!$C14 -> 0.29392196 | L79: ='Revenue, Surplus measures'!L14/'Nominal GDP'!$C14 -> 0.31717525
B80: 1982 | C80: ='Revenue, Surplus measures'!C15/'Nominal GDP'!$C15 -> -0.035458867 | I80: ='Revenue, Surplus measures'!I15/'Nominal GDP'!$C15 -> 0.30309356 | L80: ='Revenue, Surplus measures'!L15/'Nominal GDP'!$C15 -> 0.32308116
B81: 1983 | C81: ='Revenue, Surplus measures'!C16/'Nominal GDP'!$C16 -> -0.043140071 | I81: ='Revenue, Surplus measures'!I16/'Nominal GDP'!$C16 -> 0.30208221 | L81: ='Revenue, Surplus measures'!L16/'Nominal GDP'!$C16 -> 0.31455753
B82: 1984 | C82: ='Revenue, Surplus measures'!C17/'Nominal GDP'!$C17 -> -0.061071592 | I82: ='Revenue, Surplus measures'!I17/'Nominal GDP'!$C17 -> 0.28001503 | L82: ='Revenue, Surplus measures'!L17/'Nominal GDP'!$C17 -> 0.29929133
... B84: 1986 | C84: ='Revenue, Surplus measures'!C19/'Nominal GDP'!$C19 -> -0.024311692 | I84: ='Revenue, Surplus measures'!I19/'Nominal GDP'!$C19 -> 0.29184485 | L84: ='Revenue, Surplus measures'!L19/'Nominal GDP'!$C19 -> 0.32393653
B85: 1987† | C85: ='Revenue, Surplus measures'!C20/'Nominal GDP'!$C20 -> -0.03158594 | I85: ='Revenue, Surplus measures'!I20/'Nominal GDP'!$C20 -> 0.30038307 | L85: ='Revenue, Surplus measures'!L20/'Nominal GDP'!$C20 -> 0.32772246
B86: 1988† | C86: ='Revenue, Surplus measures'!C21/'Nominal GDP'!$C21 -> -0.020286341 | I86: ='Revenue, Surplus measures'!I21/'Nominal GDP'!$C21 -> 0.33035279 | L86: ='Revenue, Surplus measures'!L21/'Nominal GDP'!$C21 -> 0.36189636
B87: 1989† | C87: ='Revenue, Surplus measures'!C22/'Nominal GDP'!$C22 -> -0.013508615 | I87: ='Revenue, Surplus measures'!I22/'Nominal GDP'!$C22 -> 0.32371972 | L87: ='Revenue, Surplus measures'!L22/'Nominal GDP'!$C22 -> 0.36066488
A88: Cash, June Years | B88: 1990† | C88: ='Revenue, Surplus measures'!C23/'Nominal GDP'!$C23 -> -0.012552569 | I88: ='Revenue, Surplus measures'!I23/'Nominal GDP'!$C23 -> 0.3486585 | L88: ='Revenue, Surplus measures'!L23/'Nominal GDP'!$C23 -> 0.37731168
B89: 1991† | C89: ='Revenue, Surplus measures'!C24/'Nominal GDP'!$C24 -> -0.033676062 | I89: ='Revenue, Surplus measures'!I24/'Nominal GDP'!$C24 -> 0.33961743 | L89: ='Revenue, Surplus measures'!L24/'Nominal GDP'!$C24 -> 0.38191656
B90: 1992† | C90: ='Revenue, Surplus measures'!C25/'Nominal GDP'!$C25 -> -0.032863606 | I90: ='Revenue, Surplus measures'!I25/'Nominal GDP'!$C25 -> 0.32295512 | L90: ='Revenue, Surplus measures'!L25/'Nominal GDP'!$C25 -> 0.35925069
B91: 1993† | C91: ='Revenue, Surplus measures'!C26/'Nominal GDP'!$C26 -> -0.022974455 | I91: ='Revenue, Surplus measures'!I26/'Nominal GDP'!$C26 -> 0.32741433 | L91: ='Revenue, Surplus measures'!L26/'Nominal GDP'!$C26 -> 0.34819594
A92: IFRS, June Years | B92: 1994* | D92: ='Revenue, Surplus measures'!D27/'Nominal GDP'!$C27 -> 0.0087759064 | F92: ='Revenue, Surplus measures'!F27/'Nominal GDP'!$C27 -> -0.0060094617 | G92: ='Revenue, Surplus measures'!G27/'Nominal GDP'!$C27 -> 0.0078925039 | I92: ='Revenue, Surplus measures'!I27/'Nominal GDP'!$C27 -> 0.3204775 | J92: ='Revenue, Surplus measures'!J27/'Nominal GDP'!$C27 -> 0.3085167 | M92: ='Revenue, Surplus measures'!M27/'Nominal GDP'!$C27 -> 0.33732027
B93: 1995* | D93: ='Revenue, Surplus measures'!D28/'Nominal GDP'!$C28 -> 0.029326311 | F93: ='Revenue, Surplus measures'!F28/'Nominal GDP'!$C28 -> 0.029794226 | G93: ='Revenue, Surplus measures'!G28/'Nominal GDP'!$C28 -> 0.0043091722 | I93: ='Revenue, Surplus measures'!I28/'Nominal GDP'!$C28 -> 0.32602805 | J93: ='Revenue, Surplus measures'!J28/'Nominal GDP'!$C28 -> 0.31585362 | M93: ='Revenue, Surplus measures'!M28/'Nominal GDP'!$C28 -> 0.35323242
B94: 1996* | D94: ='Revenue, Surplus measures'!D29/'Nominal GDP'!$C29 -> 0.033966054 | F94: ='Revenue, Surplus measures'!F29/'Nominal GDP'!$C29 -> 0.030009839 | G94: ='Revenue, Surplus measures'!G29/'Nominal GDP'!$C29 -> 0.05054936 | I94: ='Revenue, Surplus measures'!I29/'Nominal GDP'!$C29 -> 0.3312459 | J94: ='Revenue, Surplus measures'!J29/'Nominal GDP'!$C29 -> 0.31745039 | M94: ='Revenue, Surplus measures'!M29/'Nominal GDP'!$C29 -> 0.34641481
B95: 1997 | D95: ='Revenue, Surplus measures'!D30/'Nominal GDP'!$C30 -> 0.018245923 | F95: ='Revenue, Surplus measures'!F30/'Nominal GDP'!$C30 -> 0.017638705 | G95: ='Revenue, Surplus measures'!G30/'Nominal GDP'!$C30 -> 0.038323295 | I95: ='Revenue, Surplus measures'!I30/'Nominal GDP'!$C30 -> 0.31076833 | J95: ='Revenue, Surplus measures'!J30/'Nominal GDP'!$C30 -> 0.30103325 | M95: ='Revenue, Surplus measures'!M30/'Nominal GDP'!$C30 -> 0.32447933 | N95: ='Revenue, Surplus measures'!N30/'Nominal GDP'!$C30 -> 0.38588671
B96: 1998 | D96: ='Revenue, Surplus measures'!D31/'Nominal GDP'!$C31 -> 0.019520006 | F96: ='Revenue, Surplus measures'!F31/'Nominal GDP'!$C31 -> 0.022350788 | G96: ='Revenue, Surplus measures'!G31/'Nominal GDP'!$C31 -> 0.0046131264 | I96: ='Revenue, Surplus measures'!I31/'Nominal GDP'!$C31 -> 0.31509369 | J96: ='Revenue, Surplus measures'!J31/'Nominal GDP'!$C31 -> 0.30289369 | M96: ='Revenue, Surplus measures'!M31/'Nominal GDP'!$C31 -> 0.32636866 | N96: ='Revenue, Surplus measures'!N31/'Nominal GDP'!$C31 -> 0.39184837
B97: 1999 | D97: ='Revenue, Surplus measures'!D32/'Nominal GDP'!$C32 -> 0.015758438 | F97: ='Revenue, Surplus measures'!F32/'Nominal GDP'!$C32 -> 0.0011830382 | G97: ='Revenue, Surplus measures'!G32/'Nominal GDP'!$C32 -> 0.018928611 | I97: ='Revenue, Surplus measures'!I32/'Nominal GDP'!$C32 -> 0.29930866 | J97: ='Revenue, Surplus measures'!J32/'Nominal GDP'!$C32 -> 0.28536175 | M97: ='Revenue, Surplus measures'!M32/'Nominal GDP'!$C32 -> 0.30388897 | N97: ='Revenue, Surplus measures'!N32/'Nominal GDP'!$C32 -> 0.36938123
B98: 2000 | D98: ='Revenue, Surplus measures'!D33/'Nominal GDP'!$C33 -> 0.012249529 | F98: ='Revenue, Surplus measures'!F33/'Nominal GDP'!$C33 -> 0.0051766902 | G98: ='Revenue, Surplus measures'!G33/'Nominal GDP'!$C33 -> -0.0033663574 | I98: ='Revenue, Surplus measures'!I33/'Nominal GDP'!$C33 -> 0.29533245 | J98: ='Revenue, Surplus measures'!J33/'Nominal GDP'!$C33 -> 0.2842915 | M98: ='Revenue, Surplus measures'!M33/'Nominal GDP'!$C33 -> 0.30476458 | N98: ='Revenue, Surplus measures'!N33/'Nominal GDP'!$C33 -> 0.36289966
B99: 2001^ | D99: ='Revenue, Surplus measures'!D34/'Nominal GDP'!$C34 -> 0.0098808598 | F99: ='Revenue, Surplus measures'!F34/'Nominal GDP'!$C34 -> 0.011631958 | G99: ='Revenue, Surplus measures'!G34/'Nominal GDP'!$C34 -> 0.0028557635 | I99: ='Revenue, Surplus measures'!I34/'Nominal GDP'!$C34 -> 0.296623 | J99: ='Revenue, Surplus measures'!J34/'Nominal GDP'!$C34 -> 0.28921765 | M99: ='Revenue, Surplus measures'!M34/'Nominal GDP'!$C34 -> 0.30964617 | N99: ='Revenue, Surplus measures'!N34/'Nominal GDP'!$C34 -> 0.367727
B100: 2002^ | D100: ='Revenue, Surplus measures'!D35/'Nominal GDP'!$C35 -> 0.017595732 | F100: ='Revenue, Surplus measures'!F35/'Nominal GDP'!$C35 -> 0.019017687 | G100: ='Revenue, Surplus measures'!G35/'Nominal GDP'!$C35 -> 0.0016622673 | I100: ='Revenue, Surplus measures'!I35/'Nominal GDP'!$C35 -> 0.29906959 | J100: ='Revenue, Surplus measures'!J35/'Nominal GDP'!$C35 -> 0.28327036 | M100: ='Revenue, Surplus measures'!M35/'Nominal GDP'!$C35 -> 0.30740159 | N100: ='Revenue, Surplus measures'!N35/'Nominal GDP'!$C35 -> 0.38227269
B101: 2003^ | D101: ='Revenue, Surplus measures'!D36/'Nominal GDP'!$C36 -> 0.01181722 | F101: ='Revenue, Surplus measures'!F36/'Nominal GDP'!$C36 -> 0.031827018 | G101: ='Revenue, Surplus measures'!G36/'Nominal GDP'!$C36 -> 0.0088718143 | I101: ='Revenue, Surplus measures'!I36/'Nominal GDP'!$C36 -> 0.29044439 | J101: ='Revenue, Surplus measures'!J36/'Nominal GDP'!$C36 -> 0.29537237 | M101: ='Revenue, Surplus measures'!M36/'Nominal GDP'!$C36 -> 0.31667633 | N101: ='Revenue, Surplus measures'!N36/'Nominal GDP'!$C36 -> 0.41052746
B102: 2004^ | D102: ='Revenue, Surplus measures'!D37/'Nominal GDP'!$C37 -> 0.049529615 | F102: ='Revenue, Surplus measures'!F37/'Nominal GDP'!$C37 -> 0.037767205 | G102: ='Revenue, Surplus measures'!G37/'Nominal GDP'!$C37 -> 0.0035238708 | I102: ='Revenue, Surplus measures'!I37/'Nominal GDP'!$C37 -> 0.28988581 | J102: ='Revenue, Surplus measures'!J37/'Nominal GDP'!$C37 -> 0.29382306 | M102: ='Revenue, Surplus measures'!M37/'Nominal GDP'!$C37 -> 0.31321432 | N102: ='Revenue, Surplus measures'!N37/'Nominal GDP'!$C37 -> 0.39835925
A103: PBE Standards, June Years | B103: 2005^ | D103: ='Revenue, Surplus measures'!D38/'Nominal GDP'!$C38 -> 0.037823969 | F103: ='Revenue, Surplus measures'!F38/'Nominal GDP'!$C38 -> 0.045118944 | G103: ='Revenue, Surplus measures'!G38/'Nominal GDP'!$C38 -> 0.01979554 | I103: ='Revenue, Surplus measures'!I38/'Nominal GDP'!$C38 -> 0.29889097 | J103: ='Revenue, Surplus measures'!J38/'Nominal GDP'!$C38 -> 0.3027238 | M103: ='Revenue, Surplus measures'!M38/'Nominal GDP'!$C38 -> 0.32403079 | N103: ='Revenue, Surplus measures'!N38/'Nominal GDP'!$C38 -> 0.41300868
B104: 2006^ | D104: ='Revenue, Surplus measures'!D39/'Nominal GDP'!$C39 -> 0.058016934 | F104: ='Revenue, Surplus measures'!F39/'Nominal GDP'!$C39 -> 0.043116235 | G104: ='Revenue, Surplus measures'!G39/'Nominal GDP'!$C39 -> 0.018149979 | I104: ='Revenue, Surplus measures'!I39/'Nominal GDP'!$C39 -> 0.30223211 | J104: ='Revenue, Surplus measures'!J39/'Nominal GDP'!$C39 -> 0.30993597 | M104: ='Revenue, Surplus measures'!M39/'Nominal GDP'!$C39 -> 0.33745584 | N104: ='Revenue, Surplus measures'!N39/'Nominal GDP'!$C39 -> 0.43045548
B105: 2007^ | D105: ='Revenue, Surplus measures'!D40/'Nominal GDP'!$C40 -> 0.045731029 | F105: ='Revenue, Surplus measures'!F40/'Nominal GDP'!$C40 -> 0.033406112 | G105: ='Revenue, Surplus measures'!G40/'Nominal GDP'!$C40 -> 0.01592206 | I105: ='Revenue, Surplus measures'!I40/'Nominal GDP'!$C40 -> 0.2973315 | J105: ='Revenue, Surplus measures'!J40/'Nominal GDP'!$C40 -> 0.30485643 | M105: ='Revenue, Surplus measures'!M40/'Nominal GDP'!$C40 -> 0.33047538 | N105: ='Revenue, Surplus measures'!N40/'Nominal GDP'!$C40 -> 0.42136737
B106: 2008^ | D106: ='Revenue, Surplus measures'!D41/'Nominal GDP'!$C41 -> 0.012618564 | E106: ='Revenue, Surplus measures'!E41/'Nominal GDP'!$C41 -> 0.030662475 | F106: ='Revenue, Surplus measures'!F41/'Nominal GDP'!$C41 -> 0.029836763 | G106: ='Revenue, Surplus measures'!G41/'Nominal GDP'!$C41 -> 0.010887746 | I106: ='Revenue, Surplus measures'!I41/'Nominal GDP'!$C41 -> 0.29200542 | J106: ='Revenue, Surplus measures'!J41/'Nominal GDP'!$C41 -> 0.3003631 | M106: ='Revenue, Surplus measures'!M41/'Nominal GDP'!$C41 -> 0.32591781 | N106: ='Revenue, Surplus measures'!N41/'Nominal GDP'!$C41 -> 0.42732152
B107: 2009^ | D107: ='Revenue, Surplus measures'!D42/'Nominal GDP'!$C42 -> -0.05532529 | E107: ='Revenue, Surplus measures'!E42/'Nominal GDP'!$C42 -> -0.020012956 | F107: ='Revenue, Surplus measures'!F42/'Nominal GDP'!$C42 -> -0.020502747 | G107: ='Revenue, Surplus measures'!G42/'Nominal GDP'!$C42 -> -0.045497875 | I107: ='Revenue, Surplus measures'!I42/'Nominal GDP'!$C42 -> 0.26922165 | J107: ='Revenue, Surplus measures'!J42/'Nominal GDP'!$C42 -> 0.28798117 | M107: ='Revenue, Surplus measures'!M42/'Nominal GDP'!$C42 -> 0.31173339 | N107: ='Revenue, Surplus measures'!N42/'Nominal GDP'!$C42 -> 0.41447358
...

Sheet Debt, Net Worth
A1: Gross Debt, Net Debt, Net Worth
A3: $ millions | C3: Gross Debt Measures | G3: Net Worth | J3: Net Debt Measures
C4: Total Crown Borrowings | D4: Gross Sovereign-issued Debt | E4: Gross debt | G4: Total Crown Net Worth | H4: Net Worth attributable to the Crown | J4: (Former) Core Crown Net Debt | K4: Core Crown Net Debt | L4: Net Debt
A5: Cash, March Years | B5: 1972 | D5: 3186.5 | E5: 3186.5 | J5: 405.083
B6: 1973 | D6: 3503.1 | E6: 3503.1 | J6: 466.983
B7: 1974 | D7: 3734.5 | E7: 3734.5 | J7: 408.695
B8: 1975 | D8: 4199.7 | E8: 4199.7 | J8: 501
B9: 1976 | D9: 5557.9 | E9: 5557.9 | J9: 985.8
B10: 1977 | D10: 6289.2 | E10: 6289.2 | J10: 1069.4
B11: 1978 | D11: 7483.8 | E11: 7483.8 | J11: 1339.3
B12: 1979 | D12: 8819.5 | E12: 8819.5 | J12: 2548.273
B13: 1980 | D13: 10346.4 | E13: 10346.4 | J13: 3226.4
B14: 1981 | D14: 11617.1 | E14: 11617.1 | J14: 4063.729
B15: 1982 | D15: 14381.4 | E15: 14381.4 | J15: 5903.384
B16: 1983 | D16: 18732.8 | E16: 18732.8 | J16: 8959.4
B17: 1984 | D17: 21878.7 | E17: 21878.7 | J17: 11029.37
... B22: 1989 | D22: 39721 | E22: 39721 | J22: 29933.637
A23: Cash, June Years | B23: 1990 | D23: 44347 | E23: 44347 | J23: 35705.695
B24: 1991 | D24: 43935 | E24: 43935 | J24: 34071.669
B25: 1992 | D25: 47105 | E25: 47105 | J25: 38414.798 | K25: 42171.798
B26: 1993 | D26: 47478 | E26: 47478 | J26: 37196 | K26: 40262
A27: IFRS, June Years | B27: 1994 | C27: 47873 | D27: 46429 | E27: 46429 | G27: -3294.9774 | J27: 35423 | K27: 38980
B28: 1995 | C28: 46145 | D28: 44529.609 | E28: 44529.609 | G28: 1438.8045 | J28: 32969.509 | K28: 38680.509
B29: 1996 | C29: 43663 | D29: 41900.731 | E29: 41900.731 | G29: 7991.1805 | J29: 28986.329 | K29: 33835.329
B30: 1997 | C30: 38968.273 | D30: 36236.273 | E30: 36236.273 | G30: 12167.053 | J30: 25561.781 | K30: 30316.781
B31: 1998 | C31: 40593.788 | D31: 38474.788 | E31: 38474.788 | G31: 14573.639 | J31: 24635.057 | K31: 30472.057
B32: 1999 | C32: 38715.333 | D32: 37307.333 | E32: 37307.333 | G32: 10792.992 | J32: 22274.782 | K32: 25922.782
B33: 2000 | C33: 37526.976 | D33: 36579.976 | E33: 36579.976 | G33: 12605.073 | J33: 21900.256 | K33: 25895.256
B34: 2001 | C34: 38129.834 | D34: 37193.834 | E34: 37193.834 | G34: 15450.219 | J34: 20292.976 | K34: 24907.976
B35: 2002 | C35: 38492.456 | D35: 36650.486 | E35: 36650.486 | G35: 22824.599 | H35: 22719 | J35: 19665.752 | K35: 25387.752
B36: 2003 | C36: 39327.22 | D36: 36617.22 | E36: 36617.22 | G36: 28012.28 | H36: 27918 | J36: 17976.723 | K36: 24530.723
B37: 2004 | C37: 37719.796 | D37: 36017.288 | E37: 36017.288 | G37: 39595.001 | H37: 39456 | J37: 15569.185 | K37: 23858.185
A38: PBE Standards, June Years | B38: 2005 | C38: 37728.361 | D38: 35477.834 | E38: 35477.834 | G38: 54240.469 | H38: 54025 | J38: 11092.976 | K38: 19878.976
B39: 2006 | C39: 40003.91 | D39: 35866.902 | E39: 33902.902 | G39: 83971 | H39: 83678 | J39: 8043.693 | K39: 16162.693
B40: 2007 | C40: 41898 | D40: 36805 | E40: 30647 | G40: 96827 | H40: 96458 | J40: 4109 | K40: 13380
B41: 2008 | C41: 46110 | D41: 37745 | E41: 31390 | G41: 105514 | H41: 105132 | J41: -19 | K41: 10258 | L41: -9479.943
B42: 2009 | C42: 61953 | D42: 50973 | E42: 43356 | G42: 99515 | H42: 99068 | J42: 6690 | K42: 17119 | L42: -1711.009
B43: 2010 | C43: 69733 | D43: 58891 | E43: 53591 | G43: 94988 | H43: 94586 | J43: 15871 | K43: 26738 | L43: 5124.895
B44: 2011 | C44: 90245 | D44: 77290 | E44: 72420 | G44: 80887 | H44: 80579 | J44: 28049 | K44: 40128 | L44: 14554.494
B45: 2012 | C45: 100534 | D45: 84168 | E45: 79635 | G45: 59780 | H45: 59348 | J45: 37347 | K45: 50671 | L45: 23893.395
B46: 2013 | C46: 100087 | D46: 84286 | E46: 77984 | G46: 70011 | H46: 68071 | J46: 42709 | K46: 55835 | L46: 25298.399
B47: 2014 | C47: 103419 | D47: 88468 | E47: 81956 | G47: 80697 | H47: 75486 | J47: 46178 | K47: 59931 | L47: 25207.866
B48: 2015 | C48: 112580 | D48: 93156 | E48: 86125 | G48: 92236 | H48: 86454 | J48: 46491 | K48: 60631 | L48: 22824.858
B49: 2016 | C49: 113956 | D49: 93283 | E49: 86928 | G49: 95521 | H49: 89366 | J49: 47268 | K49: 61880 | L49: 23192.833
B50: 2017 | C50: 111806 | D50: 92620 | E50: 87141 | G50: 116472 | H50: 110532 | J50: 47466 | K50: 59480 | L50: 16248.604
B51: 2018 | C51: 115652 | D51: 95437 | E51: 88053 | G51: 135637 | H51: 129644 | J51: 45246 | K51: 57495 | L51: 11218.778
B52: 2019 | C52: 110248 | D52: 90930 | E52: 84449 | G52: 143339 | H52: 136949 | J52: 43891 | K52: 57736 | L52: 5432.286
B53: 2020 | C53: 152717 | D53: 124145 | E53: 102257 | G53: 115943 | H53: 110320 | J53: =124145-102169+46843 -> 68819 | K53: 83375 | L53: 35710.486
B54: 2021 | C54: 162560 | D54: 131256 | E54: 100835 | G54: 157193 | H54: 151469 | J54: 83352 | K54: 102080 | L54: 35921
B55: 2022 | C55: 203965 | D55: 164038 | E55: 118950 | G55: 174319 | H55: 167036 | J55: 102770 | K55: 128873 | L55: 61850
B56: 2023* | C56: 226755 | E56: 135789 | G56: 191472 | H56: 183514 | K56: 155273 | L56: 71367
B57: 2024 | C57: 250943 | E57: 175966 | G57: 191049 | H57: 181818 | K57: 175464 | L57: 82197
B58: 2025 | C58: 272085 | E58: 203688 | G58: 189128 | H58: 179260 | K58: 182171 | L58: 88719
B60: * As part of a review of the fiscal indicators through the Budget 2022, the Gross Sovereign-issued Debt and the (former) Core Crown Net Debt (column J) measures are no longer published indicators.
A62: % GDP | C62: Gross Debt Measures | G62: Net Worth | J62: Net Debt Measures
C63: Total Crown Borrowings | D63: Gross Sovereign-issued Debt | E63: Gross debt | G63: Total Crown Net Worth | H63: Net Worth attributable to the Crown | J63: (Former) Core Crown Net Debt | K63: Core Crown Net Debt | L63: Net Debt
A64: Cash, March Years | B64: 1972 | D64: =D5/'Nominal GDP'!$C5 -> 0.45586552 | E64: =E5/'Nominal GDP'!$C5 -> 0.45586552 | J64: =J5/'Nominal GDP'!$C5 -> 0.057951788
B65: 1973 | D65: =D6/'Nominal GDP'!$C6 -> 0.43355198 | E65: =E6/'Nominal GDP'!$C6 -> 0.43355198 | J65: =J6/'Nominal GDP'!$C6 -> 0.057794926
B66: 1974 | D66: =D7/'Nominal GDP'!$C7 -> 0.39894242 | E66: =E7/'Nominal GDP'!$C7 -> 0.39894242 | J66: =J7/'Nominal GDP'!$C7 -> 0.043659331
B67: 1975 | D67: =D8/'Nominal GDP'!$C8 -> 0.41161423 | E67: =E8/'Nominal GDP'!$C8 -> 0.41161423 | J67: =J8/'Nominal GDP'!$C8 -> 0.049103205
B68: 1976 | D68: =D9/'Nominal GDP'!$C9 -> 0.48304363 | E68: =E9/'Nominal GDP'!$C9 -> 0.48304363 | J68: =J9/'Nominal GDP'!$C9 -> 0.085677038
B69: 1977 | D69: =D10/'Nominal GDP'!$C10 -> 0.45012883 | E69: =E10/'Nominal GDP'!$C10 -> 0.45012883 | J69: =J10/'Nominal GDP'!$C10 -> 0.076538792
B70: 1978 | D70: =D11/'Nominal GDP'!$C11 -> 0.4776792 | E70: =E11/'Nominal GDP'!$C11 -> 0.4776792 | J70: =J11/'Nominal GDP'!$C11 -> 0.085485415
B71: 1979 | D71: =D12/'Nominal GDP'!$C12 -> 0.49519933 | E71: =E12/'Nominal GDP'!$C12 -> 0.49519933 | J71: =J12/'Nominal GDP'!$C12 -> 0.14308102
B72: 1980 | D72: =D13/'Nominal GDP'!$C13 -> 0.50357247 | E72: =E13/'Nominal GDP'!$C13 -> 0.50357247 | J72: =J13/'Nominal GDP'!$C13 -> 0.157033
B73: 1981 | D73: =D14/'Nominal GDP'!$C14 -> 0.48428798 | E73: =E14/'Nominal GDP'!$C14 -> 0.48428798 | J73: =J14/'Nominal GDP'!$C14 -> 0.16940675
B74: 1982 | D74: =D15/'Nominal GDP'!$C15 -> 0.495432 | E74: =E15/'Nominal GDP'!$C15 -> 0.495432 | J74: =J15/'Nominal GDP'!$C15 -> 0.20336861
B75: 1983 | D75: =D16/'Nominal GDP'!$C16 -> 0.56042602 | E75: =E16/'Nominal GDP'!$C16 -> 0.56042602 | J75: =J16/'Nominal GDP'!$C16 -> 0.26803686
B76: 1984 | D76: =D17/'Nominal GDP'!$C17 -> 0.58730035 | E76: =E17/'Nominal GDP'!$C17 -> 0.58730035 | J76: =J17/'Nominal GDP'!$C17 -> 0.29606663
... B81: 1989 | D81: =D22/'Nominal GDP'!$C22 -> 0.56238939 | E81: =E22/'Nominal GDP'!$C22 -> 0.56238939 | J81: =J22/'Nominal GDP'!$C22 -> 0.4238151
A82: Cash, June Years | B82: 1990 | D82: =D23/'Nominal GDP'!$C23 -> 0.59019164 | E82: =E23/'Nominal GDP'!$C23 -> 0.59019164 | J82: =J23/'Nominal GDP'!$C23 -> 0.47518891
B83: 1991 | D83: =D24/'Nominal GDP'!$C24 -> 0.57840414 | E83: =E24/'Nominal GDP'!$C24 -> 0.57840414 | J83: =J24/'Nominal GDP'!$C24 -> 0.44855342
B84: 1992 | D84: =D25/'Nominal GDP'!$C25 -> 0.61235765 | E84: =E25/'Nominal GDP'!$C25 -> 0.61235765 | J84: =J25/'Nominal GDP'!$C25 -> 0.49938638 | L84: =L25/'Nominal GDP'!$C25 -> 0
B85: 1993 | D85: =D26/'Nominal GDP'!$C26 -> 0.59834402 | E85: =E26/'Nominal GDP'!$C26 -> 0.59834402 | J85: =J26/'Nominal GDP'!$C26 -> 0.46876457 | L85: =L26/'Nominal GDP'!$C26 -> 0
A86: IFRS, June Years | B86: 1994 | C86: =C27/'Nominal GDP'!$C27 -> 0.55646221 | D86: =D27/'Nominal GDP'!$C27 -> 0.53967756 | E86: =E27/'Nominal GDP'!$C27 -> 0.53967756 | G86: =G27/'Nominal GDP'!$C27 -> -0.038299885 | J86: =J27/'Nominal GDP'!$C27 -> 0.41174693 | L86: =L27/'Nominal GDP'!$C27 -> 0
B87: 1995 | C87: =C28/'Nominal GDP'!$C28 -> 0.50213826 | D87: =D28/'Nominal GDP'!$C28 -> 0.48455999 | E87: =E28/'Nominal GDP'!$C28 -> 0.48455999 | G87: =G28/'Nominal GDP'!$C28 -> 0.015656708 | J87: =J28/'Nominal GDP'!$C28 -> 0.35876589 | L87: =L28/'Nominal GDP'!$C28 -> 0
B88: 1996 | C88: =C29/'Nominal GDP'!$C29 -> 0.44751353 | D88: =D29/'Nominal GDP'!$C29 -> 0.42945157 | E88: =E29/'Nominal GDP'!$C29 -> 0.42945157 | G88: =G29/'Nominal GDP'!$C29 -> 0.081903703 | J88: =J29/'Nominal GDP'!$C29 -> 0.29708848 | L88: =L29/'Nominal GDP'!$C29 -> 0
B89: 1997 | C89: =C30/'Nominal GDP'!$C30 -> 0.38164902 | D89: =D30/'Nominal GDP'!$C30 -> 0.35489225 | E89: =E30/'Nominal GDP'!$C30 -> 0.35489225 | G89: =G30/'Nominal GDP'!$C30 -> 0.11916216 | J89: =J30/'Nominal GDP'!$C30 -> 0.25034798 | L89: =L30/'Nominal GDP'!$C30 -> 0
B90: 1998 | C90: =C31/'Nominal GDP'!$C31 -> 0.38690966 | D90: =D31/'Nominal GDP'!$C31 -> 0.36671294 | E90: =E31/'Nominal GDP'!$C31 -> 0.36671294 | G90: =G31/'Nominal GDP'!$C31 -> 0.13890504 | J90: =J31/'Nominal GDP'!$C31 -> 0.23480296 | L90: =L31/'Nominal GDP'!$C31 -> 0
B91: 1999 | C91: =C32/'Nominal GDP'!$C32 -> 0.35782592 | D91: =D32/'Nominal GDP'!$C32 -> 0.3448125 | E91: =E32/'Nominal GDP'!$C32 -> 0.3448125 | G91: =G32/'Nominal GDP'!$C32 -> 0.09975408 | J91: =J32/'Nominal GDP'!$C32 -> 0.20587436 | L91: =L32/'Nominal GDP'!$C32 -> 0
B92: 2000 | C92: =C33/'Nominal GDP'!$C33 -> 0.32727775 | D92: =D33/'Nominal GDP'!$C33 -> 0.31901884 | E92: =E33/'Nominal GDP'!$C33 -> 0.31901884 | G92: =G33/'Nominal GDP'!$C33 -> 0.10993052 | J92: =J33/'Nominal GDP'!$C33 -> 0.19099505 | L92: =L33/'Nominal GDP'!$C33 -> 0
B93: 2001 | C93: =C34/'Nominal GDP'!$C34 -> 0.31200512 | D93: =D34/'Nominal GDP'!$C34 -> 0.30434611 | E93: =E34/'Nominal GDP'!$C34 -> 0.30434611 | G93: =G34/'Nominal GDP'!$C34 -> 0.12642456 | J93: =J34/'Nominal GDP'!$C34 -> 0.1660514 | L93: =L34/'Nominal GDP'!$C34 -> 0
B94: 2002 | C94: =C35/'Nominal GDP'!$C35 -> 0.2962257 | D94: =D35/'Nominal GDP'!$C35 -> 0.28205048 | E94: =E35/'Nominal GDP'!$C35 -> 0.28205048 | G94: =G35/'Nominal GDP'!$C35 -> 0.17565086 | H94: =H35/'Nominal GDP'!$C35 -> 0.1748382 | J94: =J35/'Nominal GDP'!$C35 -> 0.15134137 | L94: =L35/'Nominal GDP'!$C35 -> 0
B95: 2003 | C95: =C36/'Nominal GDP'!$C36 -> 0.2866917 | D95: =D36/'Nominal GDP'!$C36 -> 0.26693605 | E95: =E36/'Nominal GDP'!$C36 -> 0.26693605 | G95: =G36/'Nominal GDP'!$C36 -> 0.20420686 | H95: =H36/'Nominal GDP'!$C36 -> 0.20351957 | J95: =J36/'Nominal GDP'!$C36 -> 0.1310486 | L95: =L36/'Nominal GDP'!$C36 -> 0
B96: 2004 | C96: =C37/'Nominal GDP'!$C37 -> 0.25561479 | D96: =D37/'Nominal GDP'!$C37 -> 0.24407744 | E96: =E37/'Nominal GDP'!$C37 -> 0.24407744 | G96: =G37/'Nominal GDP'!$C37 -> 0.26832244 | H96: =H37/'Nominal GDP'!$C37 -> 0.26738048 | J96: =J37/'Nominal GDP'!$C37 -> 0.1055073 | L96: =L37/'Nominal GDP'!$C37 -> 0
A97: PBE Standards, June Years | B97: 2005 | C97: =C38/'Nominal GDP'!$C38 -> 0.24060994 | D97: =D38/'Nominal GDP'!$C38 -> 0.22625737 | E97: =E38/'Nominal GDP'!$C38 -> 0.22625737 | G97: =G38/'Nominal GDP'!$C38 -> 0.34591474 | H97: =H38/'Nominal GDP'!$C38 -> 0.3445406 | J97: =J38/'Nominal GDP'!$C38 -> 0.070744667 | K97: =K38/'Nominal GDP'!$C38 -> 0.12677676 | L97: =L38/'Nominal GDP'!$C38 -> 0
B98: 2006 | C98: =C39/'Nominal GDP'!$C39 -> 0.24323957 | D98: =D39/'Nominal GDP'!$C39 -> 0.21808493 | E98: =E39/'Nominal GDP'!$C39 -> 0.20614304 | G98: =G39/'Nominal GDP'!$C39 -> 0.51057685 | H98: =H39/'Nominal GDP'!$C39 -> 0.50879529 | J98: =J39/'Nominal GDP'!$C39 -> 0.048908831 | K98: =K39/'Nominal GDP'!$C39 -> 0.098275557 | L98: =L39/'Nominal GDP'!$C39 -> 0
B99: 2007 | C99: =C40/'Nominal GDP'!$C40 -> 0.238848 | D99: =D40/'Nominal GDP'!$C40 -> 0.20981433 | E99: =E40/'Nominal GDP'!$C40 -> 0.17470941 | G99: =G40/'Nominal GDP'!$C40 -> 0.55198185 | H99: =H40/'Nominal GDP'!$C40 -> 0.54987829 | J99: =J40/'Nominal GDP'!$C40 -> 0.023424184 | K99: =K40/'Nominal GDP'!$C40 -> 0.07627539 | L99: =L40/'Nominal GDP'!$C40 -> 0
B100: 2008 | C100: =C41/'Nominal GDP'!$C41 -> 0.24406123 | D100: =D41/'Nominal GDP'!$C41 -> 0.1997851 | E100: =E41/'Nominal GDP'!$C41 -> 0.16614795 | G100: =G41/'Nominal GDP'!$C41 -> 0.55848789 | H100: =H41/'Nominal GDP'!$C41 -> 0.55646596 | J100: =J41/'Nominal GDP'!$C41 -> -0.00010056741 | K100: =K41/'Nominal GDP'!$C41 -> 0.054295816 | L100: =L41/'Nominal GDP'!$C41 -> -0.050177544
B101: 2009 | C101: =C42/'Nominal GDP'!$C42 -> 0.32627964 | D101: =D42/'Nominal GDP'!$C42 -> 0.26845274 | E101: =E42/'Nominal GDP'!$C42 -> 0.22833729 | G101: =G42/'Nominal GDP'!$C42 -> 0.52410245 | H101: =H42/'Nominal GDP'!$C42 -> 0.52174829 | J101: =J42/'Nominal GDP'!$C42 -> 0.035233335 | K101: =K42/'Nominal GDP'!$C42 -> 0.090158366 | L101: =L42/'Nominal GDP'!$C42 -> -0.0090111441
B102: 2010 | C102: =C43/'Nominal GDP'!$C43 -> 0.35333968 | D102: =D43/'Nominal GDP'!$C43 -> 0.29840287 | E102: =E43/'Nominal GDP'!$C43 -> 0.27154757 | G102: =G43/'Nominal GDP'!$C43 -> 0.4813077 | H102: =H43/'Nominal GDP'!$C43 -> 0.47927075 | J102: =J43/'Nominal GDP'!$C43 -> 0.080418943 | K102: =K43/'Nominal GDP'!$C43 -> 0.13548243 | L102: =L43/'Nominal GDP'!$C43 -> 0.025968032
B103: 2011 | C103: =C44/'Nominal GDP'!$C44 -> 0.43783385 | D103: =D44/'Nominal GDP'!$C44 -> 0.3749812 | E103: =E44/'Nominal GDP'!$C44 -> 0.35135384 | G103: =G44/'Nominal GDP'!$C44 -> 0.39243245 | H103: =H44/'Nominal GDP'!$C44 -> 0.39093816 | J103: =J44/'Nominal GDP'!$C44 -> 0.1360829 | K103: =K44/'Nominal GDP'!$C44 -> 0.19468554 | L103: =L44/'Nominal GDP'!$C44 -> 0.070612778
B104: 2012 | C104: =C45/'Nominal GDP'!$C45 -> 0.46718062 | D104: =D45/'Nominal GDP'!$C45 -> 0.39112796 | E104: =E45/'Nominal GDP'!$C45 -> 0.37006315 | G104: =G45/'Nominal GDP'!$C45 -> 0.27779714 | H104: =H45/'Nominal GDP'!$C45 -> 0.27578964 | J104: =J45/'Nominal GDP'!$C45 -> 0.17355118 | K104: =K45/'Nominal GDP'!$C45 -> 0.2354677 | L104: =L45/'Nominal GDP'!$C45 -> 0.1110324
B105: 2013 | C105: =C46/'Nominal GDP'!$C46 -> 0.45663669 | D105: =D46/'Nominal GDP'!$C46 -> 0.38454625 | E105: =E46/'Nominal GDP'!$C46 -> 0.35579402 | G105: =G46/'Nominal GDP'!$C46 -> 0.31941802 | H105: =H46/'Nominal GDP'!$C46 -> 0.31056697 | J105: =J46/'Nominal GDP'!$C46 -> 0.19485544 | K105: =K46/'Nominal GDP'!$C46 -> 0.25474147 | L105: =L46/'Nominal GDP'!$C46 -> 0.11542136
B106: 2014 | C106: =C47/'Nominal GDP'!$C47 -> 0.43613154 | D106: =D47/'Nominal GDP'!$C47 -> 0.37308121 | E106: =E47/'Nominal GDP'!$C47 -> 0.34561924 | G106: =G47/'Nominal GDP'!$C47 -> 0.34030987 | H106: =H47/'Nominal GDP'!$C47 -> 0.3183344 | J106: =J47/'Nominal GDP'!$C47 -> 0.19473871 | K106: =K47/'Nominal GDP'!$C47 -> 0.25273692 | L106: =L47/'Nominal GDP'!$C47 -> 0.10630489
B107: 2015 | C107: =C48/'Nominal GDP'!$C48 -> 0.45787866 | D107: =D48/'Nominal GDP'!$C48 -> 0.37887853 | E107: =E48/'Nominal GDP'!$C48 -> 0.35028246 | G107: =G48/'Nominal GDP'!$C48 -> 0.37513676 | H107: =H48/'Nominal GDP'!$C48 -> 0.35162055 | J107: =J48/'Nominal GDP'!$C48 -> 0.18908542 | K107: =K48/'Nominal GDP'!$C48 -> 0.24659479 | L107: =L48/'Nominal GDP'!$C48 -> 0.092831901
B108: 2016 | C108: =C49/'Nominal GDP'!$C49 -> 0.4401358 | D108: =D49/'Nominal GDP'!$C49 -> 0.36028983 | E108: =E49/'Nominal GDP'!$C49 -> 0.33574472 | G108: =G49/'Nominal GDP'!$C49 -> 0.36893373 | H108: =H49/'Nominal GDP'!$C49 -> 0.34516108 | J108: =J49/'Nominal GDP'!$C49 -> 0.18256467 | K108: =K49/'Nominal GDP'!$C49 -> 0.23900105 | L108: =L49/'Nominal GDP'!$C49 -> 0.0895784
B109: 2017 | C109: =C50/'Nominal GDP'!$C50 -> 0.40543941 | D109: =D50/'Nominal GDP'!$C50 -> 0.33586568 | E109: =E50/'Nominal GDP'!$C50 -> 0.31599732 | G109: =G50/'Nominal GDP'!$C50 -> 0.42235962 | H109: =H50/'Nominal GDP'!$C50 -> 0.40081954 | J109: =J50/'Nominal GDP'!$C50 -> 0.17212482 | K109: =K50/'Nominal GDP'!$C50 -> 0.2156909 | L109: =L50/'Nominal GDP'!$C50 -> 0.058921923
... B113: 2021 | C113: =C54/'Nominal GDP'!$C54 -> 0.47354515 | D113: =D54/'Nominal GDP'!$C54 -> 0.38235508 | E113: =E54/'Nominal GDP'!$C54 -> 0.29373724 | G113: =G54/'Nominal GDP'!$C54 -> 0.45791082 | H113: =H54/'Nominal GDP'!$C54 -> 0.44123653 | J113: =J54/'Nominal GDP'!$C54 -> 0.24280841 | K113: =K54/'Nominal GDP'!$C54 -> 0.29736398 | L113: =L54/'Nominal GDP'!$C54 -> 0.10463961
B114: 2022 | C114: =C55/'Nominal GDP'!$C55 -> 0.55767454 | D114: 0.45643832 | E114: =E55/'Nominal GDP'!$C55 -> 0.32522926 | G114: =G55/'Nominal GDP'!$C55 -> 0.4766174 | H114: =H55/'Nominal GDP'!$C55 -> 0.45670445 | J114: =J55/'Nominal GDP'!$C55 -> 0.28099042 | K114: =K55/'Nominal GDP'!$C55 -> 0.35236041 | L114: =L55/'Nominal GDP'!$C55 -> 0.16910828
...

Sheet NZS Fund series
A1: NZS Fund
A3: $ millions | C3: NZS Fund series
C4: NZS Fund Revenue | D4: Crown contributions to the NZS Fund | E4: NZS Fund Current Tax expense | F4: NZS Fund Other Expenses and movements* | G4: NZS Fund Gains/(losses) | H4: NZS Fund Net worth
A5: Cash, March Years | B5: 1972
B6: 1973
B7: 1974
B8: 1975
B9: 1976
B10: 1977
B11: 1978
B12: 1979
B13: 1980
B14: 1981
B15: 1982
B16: 1983
B17: 1984
... B22: 1989
A23: Cash, June Years | B23: 1990
B24: 1991
B25: 1992
B26: 1993
A27: IFRS, June Years | B27: 1994
B28: 1995
B29: 1996
B30: 1997
B31: 1998
B32: 1999
B33: 2000
B34: 2001
B35: 2002 | C35: 15 | D35: 600 | E35: 0 | F35: 0 | G35: 0 | H35: 615
B36: 2003 | C36: 69 | D36: 1200 | E36: 0 | F36: 0 | G36: 0 | H36: 1884
B37: 2004 | C37: 131 | D37: 1879 | E37: 77 | F37: 7 | G37: 146 | H37: 3956
A38: PBE Standards, June Years | B38: 2005 | C38: 191 | D38: 2107 | E38: 234 | F38: 22 | G38: 557 | H38: 6555
B39: 2006 | C39: 359 | D39: 2337 | E39: 468 | F39: 58 | G39: 1130 | H39: 9855
B40: 2007 | C40: 436 | D40: 2049 | E40: 707 | F40: -28 | G40: 1313 | H40: 12973
B41: 2008 | C41: 385 | D41: 2104 | E41: 237 | F41: 18 | G41: -995 | H41: 14212
B42: 2009 | C42: 383 | D42: 2243 | E42: 4 | F42: -349 | G42: -3495 | H42: 13688
B43: 2010 | C43: 433 | D43: 250 | E43: -27 | F43: 492 | G43: 1750 | H43: 15656
B44: 2011 | C44: 518 | D44: 0 | E44: 872 | F44: 168 | G44: 3518 | H44: 18652
B45: 2012 | C45: 539 | D45: 0 | E45: 160 | F45: 124 | G45: -204 | H45: 18703
B46: 2013 | C46: 595 | D46: 0 | E46: 983 | F46: 140 | G46: 4374 | H46: 22549
B47: 2014 | C47: 767 | D47: 0 | E47: 1074 | F47: 164 | G47: 3735 | H47: 25809
B48: 2015 | C48: 760 | D48: 0 | E48: 46 | F48: 198 | G48: 3156 | H48: 29522
B49: 2016 | C49: 752 | D49: 0 | E49: 512 | F49: 138 | G49: -76 | H49: 29527
B50: 2017 | C50: 833 | D50: 0 | E50: 1139 | F50: 227 | G50: 5512 | H50: 34506
... B58: 2025 | C58: 1784 | D58: 879 | E58: 1755 | F58: 193 | G58: 7313 | H58: 82847
A60: * This includes deferred tax expenses which can be variable year on year.
A62: % GDP | C62: NZS Fund series
C63: NZS Fund Revenue | D63: Crown contributions to the NZS Fund | E63: NZS Fund Tax expense | F63: NZS Fund Other Expenses and movements | G63: NZS Fund Gains/(losses) | H63: NZS Fund Net worth
A64: Cash, March Years | B64: 1972
B65: 1973
B66: 1974
B67: 1975
B68: 1976
B69: 1977
B70: 1978
B71: 1979
B72: 1980
B73: 1981
B74: 1982
B75: 1983
B76: 1984
... B81: 1989
A82: Cash, June Years | B82: 1990
B83: 1991
B84: 1992
B85: 1993
A86: IFRS, June Years | B86: 1994
B87: 1995
B88: 1996
B89: 1997
B90: 1998
B91: 1999
B92: 2000
B93: 2001
B94: 2002 | C94: =C35/'Nominal GDP'!$C35 -> 0.00011543523 | D94: =D35/'Nominal GDP'!$C35 -> 0.0046174092 | E94: =E35/'Nominal GDP'!$C35 -> 0 | F94: =F35/'Nominal GDP'!$C35 -> 0 | G94: =G35/'Nominal GDP'!$C35 -> 0 | H94: =H35/'Nominal GDP'!$C35 -> 0.0047328444
B95: 2003 | C95: =C36/'Nominal GDP'!$C36 -> 0.00050300344 | D95: =D36/'Nominal GDP'!$C36 -> 0.0087478859 | E95: =E36/'Nominal GDP'!$C36 -> 0 | F95: =F36/'Nominal GDP'!$C36 -> 0 | G95: =G36/'Nominal GDP'!$C36 -> 0 | H95: =H36/'Nominal GDP'!$C36 -> 0.013734181
B96: 2004 | C96: =C37/'Nominal GDP'!$C37 -> 0.00088774438 | D96: =D37/'Nominal GDP'!$C37 -> 0.012733372 | E96: =E37/'Nominal GDP'!$C37 -> 0.00052180395 | F96: =F37/'Nominal GDP'!$C37 -> 4.7436723e-05 | G96: =G37/'Nominal GDP'!$C37 -> 0.0009893945 | H96: =H37/'Nominal GDP'!$C37 -> 0.026808525
A97: PBE Standards, June Years | B97: 2005 | C97: =C38/'Nominal GDP'!$C38 -> 0.0012180889 | D97: =D38/'Nominal GDP'!$C38 -> 0.013437243 | E97: =E38/'Nominal GDP'!$C38 -> 0.0014923184 | F97: =F38/'Nominal GDP'!$C38 -> 0.00014030344 | G97: =G38/'Nominal GDP'!$C38 -> 0.003552228 | H97: =H38/'Nominal GDP'!$C38 -> 0.041804047
B98: 2006 | C98: =C39/'Nominal GDP'!$C39 -> 0.0021828618 | D98: =D39/'Nominal GDP'!$C39 -> 0.014209883 | E98: =E39/'Nominal GDP'!$C39 -> 0.0028456249 | F98: =F39/'Nominal GDP'!$C39 -> 0.00035266291 | G98: =G39/'Nominal GDP'!$C39 -> 0.0068708463 | H98: =H39/'Nominal GDP'!$C39 -> 0.059922293
B99: 2007 | C99: =C40/'Nominal GDP'!$C40 -> 0.002485506 | D99: =D40/'Nominal GDP'!$C40 -> 0.011680738 | E99: =E40/'Nominal GDP'!$C40 -> 0.0040303961 | F99: =F40/'Nominal GDP'!$C40 -> -0.00015961965 | G99: =G40/'Nominal GDP'!$C40 -> 0.0074850214 | H99: =H40/'Nominal GDP'!$C40 -> 0.073955204
B100: 2008 | C100: =C41/'Nominal GDP'!$C41 -> 0.0020378133 | D100: =D41/'Nominal GDP'!$C41 -> 0.011136518 | E100: =E41/'Nominal GDP'!$C41 -> 0.0012544461 | F100: =F41/'Nominal GDP'!$C41 -> 9.527439e-05 | G100: =G41/'Nominal GDP'!$C41 -> -0.0052665566 | H100: =H41/'Nominal GDP'!$C41 -> 0.075224424
B101: 2009 | C101: =C42/'Nominal GDP'!$C42 -> 0.0020170953 | D101: =D42/'Nominal GDP'!$C42 -> 0.01181291 | E101: =E42/'Nominal GDP'!$C42 -> 2.1066269e-05 | F101: =F42/'Nominal GDP'!$C42 -> -0.001838032 | G101: =G42/'Nominal GDP'!$C42 -> -0.018406653 | H101: =H42/'Nominal GDP'!$C42 -> 0.072088773
B102: 2010 | C102: =C43/'Nominal GDP'!$C43 -> 0.002194027 | D102: =D43/'Nominal GDP'!$C43 -> 0.0012667592 | E102: =E43/'Nominal GDP'!$C43 -> -0.00013681 | F102: =F43/'Nominal GDP'!$C43 -> 0.0024929822 | G102: =G43/'Nominal GDP'!$C43 -> 0.0088673146 | H102: =H43/'Nominal GDP'!$C43 -> 0.07932953
B103: 2011 | C103: =C44/'Nominal GDP'!$C44 -> 0.0025131357 | D103: =D44/'Nominal GDP'!$C44 -> 0 | E103: =E44/'Nominal GDP'!$C44 -> 0.0042306069 | F103: =F44/'Nominal GDP'!$C44 -> 0.00081507105 | G103: =G44/'Nominal GDP'!$C44 -> 0.017067976 | H103: =H44/'Nominal GDP'!$C44 -> 0.090492293
B104: 2012 | C104: =C45/'Nominal GDP'!$C45 -> 0.0025047283 | D104: =D45/'Nominal GDP'!$C45 -> 0 | E104: =E45/'Nominal GDP'!$C45 -> 0.00074351861 | F104: =F45/'Nominal GDP'!$C45 -> 0.00057622692 | G104: =G45/'Nominal GDP'!$C45 -> -0.00094798623 | H104: =H45/'Nominal GDP'!$C45 -> 0.086912678
B105: 2013 | C105: =C46/'Nominal GDP'!$C46 -> 0.0027146266 | D105: =D46/'Nominal GDP'!$C46 -> 0 | E105: =E46/'Nominal GDP'!$C46 -> 0.0044848369 | F105: =F46/'Nominal GDP'!$C46 -> 0.00063873567 | G105: =G46/'Nominal GDP'!$C46 -> 0.019955927 | H105: =H46/'Nominal GDP'!$C46 -> 0.1028775
B106: 2014 | C106: =C47/'Nominal GDP'!$C47 -> 0.00323454 | D106: =D47/'Nominal GDP'!$C47 -> 0 | E106: =E47/'Nominal GDP'!$C47 -> 0.0045291994 | F106: =F47/'Nominal GDP'!$C47 -> 0.00069160959 | G106: =G47/'Nominal GDP'!$C47 -> 0.015750987 | H106: =H47/'Nominal GDP'!$C47 -> 0.10883995
B107: 2015 | C107: =C48/'Nominal GDP'!$C48 -> 0.0030910267 | D107: =D48/'Nominal GDP'!$C48 -> 0 | E107: =E48/'Nominal GDP'!$C48 -> 0.00018708846 | F107: =F48/'Nominal GDP'!$C48 -> 0.00080529379 | G107: =G48/'Nominal GDP'!$C48 -> 0.012835895 | H107: =H48/'Nominal GDP'!$C48 -> 0.12007012
B108: 2016 | C108: =C49/'Nominal GDP'!$C49 -> 0.002904473 | D108: =D49/'Nominal GDP'!$C49 -> 0 | E108: =E49/'Nominal GDP'!$C49 -> 0.0019775135 | F108: =F49/'Nominal GDP'!$C49 -> 0.00053300169 | G108: =G49/'Nominal GDP'!$C49 -> -0.00029353716 | H108: =H49/'Nominal GDP'!$C49 -> 0.11404305
B109: 2017 | C109: =C50/'Nominal GDP'!$C50 -> 0.0030206879 | D109: =D50/'Nominal GDP'!$C50 -> 0 | E109: =E50/'Nominal GDP'!$C50 -> 0.0041303284 | F109: =F50/'Nominal GDP'!$C50 -> 0.00082316465 | G109: =G50/'Nominal GDP'!$C50 -> 0.019988033 | H109: =H50/'Nominal GDP'!$C50 -> 0.12512828
... B117: 2025 | C117: =C58/'Nominal GDP'!$C58 -> 0.0040907767 | D117: =D58/'Nominal GDP'!$C58 -> 0.0020155789 | E117: =E58/'Nominal GDP'!$C58 -> 0.0040242787 | F117: =F58/'Nominal GDP'!$C58 -> 0.000442556 | G117: =G58/'Nominal GDP'!$C58 -> 0.016768974 | H117: =H58/'Nominal GDP'!$C58 -> 0.18997118

Sheet Nominal GDP
A1: Gross Domestic Product
A3: $ millions | C3: Nominal GDP
A5: March Years | B5: 1972 | C5: 6990
B6: 1973 | C6: 8080
B7: 1974 | C7: 9361
B8: 1975 | C8: 10203
B9: 1976 | C9: 11506
B10: 1977 | C10: 13972
B11: 1978 | C11: 15667
B12: 1979 | C12: 17810
B13: 1980 | C13: 20546
B14: 1981 | C14: 23988
B15: 1982 | C15: 29028
B16: 1983 | C16: 33426
B17: 1984 | C17: 37253
... B22: 1989 | C22: 70629
A23: June Years | B23: 1990 | C23: 75140
B24: 1991 | C24: 75959
B25: 1992 | C25: 76924
B26: 1993 | C26: 79349
B27: 1994 | C27: 86031
B28: 1995 | C28: 91897
B29: 1996 | C29: 97568
B30: 1997 | C30: 102105
B31: 1998 | C31: 104918
B32: 1999 | C32: 108196
B33: 2000 | C33: 114664
B34: 2001 | C34: 122209
B35: 2002 | C35: 129943
... B58: 2025 | C58: 436103
